Workbook

Sheet 2024
A1: # | B1: Valor Bruto | C1: Descuento | D1: Nombre de cliente/proveedor | E1: Subtotal | F1: Impuesto | G1: ReteFuente | H1: Rete IVA | I1: Rete ICA | J1: Total Reteciones | K1: Total Documento | L1: Cod SN | M1: NIT | N1: City | O1: Vendedor en doc | P1: Vendedor Actual | Q1: Canal de Cliente | R1: PARTICIPACION CLIENTE
A2: 1247 | B2: 2.3925762e+09 | C2: 89357047 | D2: M SIERRA FERRETEROS S.A.S. "MONTEVIDEO" | E2: 2.3032191e+09 | F2: 4.3761164e+08 | G2: 55624645 | H2: 0 | I2: 0 | J2: 55624645 | K2: 2.6852061e+09 | L2: 90134981300 | M2: 901349813-9 | N2: BOGOTA - BOGOTA | O2: GRANDES CUENTAS | P2: GRANDES CUENTAS | Q2: MAYORISTA INDUSTRIAL | R2: =E2/$E$2034 -> 0.045879949
A3: 307 | B3: 1.9321613e+09 | C3: 464046.78 | D3: CENTRO PINTUCOLOR S.A.S. | E3: 1.9316973e+09 | F3: 3.6702249e+08 | G3: 44148359 | H3: 0 | I3: 0 | J3: 44148359 | K3: 2.2545714e+09 | L3: 90058246400 | M3: 900582464-5 | N3: BARRANCABERMEJA - SANTANDER | O3: EVELIO GARCIA - SANTANDER | P3: EVELIO GARCIA - SANTANDER | Q3: GRAN DISTRIBUIDOR | R3: =E3/$E$2034 -> 0.038479263
A4: 1273 | B4: 1153020562 | C4: 14940866 | D4: MARTILLO DISTRIBUIDOR MAYORISTA S.A.S. | E4: 1.1380797e+09 | F4: 2.1623514e+08 | G4: 26494247 | H4: 0 | I4: 0 | J4: 26494247 | K4: 1.3278206e+09 | L4: 90144410400 | M4: 901444104-1 | N4: CALI - VALLE DEL CAUCA | O4: JORGE CASTRO - VALLE DE CAUCA | P4: JORGE CASTRO - VALLE DE CAUCA | Q4: MAYORISTA INDUSTRIAL | R4: =E4/$E$2034 -> 0.022670461
A5: 1292 | B5: 1062240262 | C5: 2349974.6 | D5: MATERIALES SU CONSTRUCCION S.A. | E5: 1.0598903e+09 | F5: 2.0137915e+08 | G5: 22679976 | H5: 0 | I5: 0 | J5: 22679976 | K5: 1.2385895e+09 | L5: 80014765000 | M5: 800147650-1 | N5: MEDELLIN - ANTIOQUIA | O5: ANTIOQUIA | P5: ANTIOQUIA | Q5: MAYORISTA INDUSTRIAL | R5: =E5/$E$2034 -> 0.021112934
A6: 609 | B6: 986195843 | C6: 2914125.9 | D6: FEDUSE S.A.S | E6: 9.8328172e+08 | F6: 1.8682353e+08 | G6: 22838255 | H6: 0 | I6: 0 | J6: 22838255 | K6: 1.147267e+09 | L6: 89130321200 | M6: 891303212-9 | N6: GUADALAJARA DE BUGA - VALLE DE | O6: JORGE CASTRO - VALLE DE CAUCA | P6: JORGE CASTRO - VALLE DE CAUCA | Q6: GRAN DISTRIBUIDOR | R6: =E6/$E$2034 -> 0.019586897
A7: 736 | B7: 954636523 | C7: 4799038.1 | D7: FERRETERIA TUBOLAMINAS S A-CALI | E7: 9.4983748e+08 | F7: 1.8046912e+08 | G7: 22337185 | H7: 25645302 | I7: 0 | J7: 47982487 | K7: 1.0823241e+09 | L7: 89032442001 | M7: 890324420-0 | N7: CALI - VALLE DEL CAUCA | O7: JORGE CASTRO - VALLE DE CAUCA | P7: JORGE CASTRO - VALLE DE CAUCA | Q7: GRAN DISTRIBUIDOR | R7: =E7/$E$2034 -> 0.01892069
A8: 1051 | B8: 929659150 | C8: 8664023.3 | D8: INDURRUEDAS S A S "BMANGA" | E8: 9.2099513e+08 | F8: 1.7498907e+08 | G8: 19642262 | H8: 0 | I8: 0 | J8: 19642262 | K8: 1.0763419e+09 | L8: 89020795600 | M8: 890207956-5 | N8: BUCARAMANGA - SANTANDER | O8: EVELIO GARCIA - SANTANDER | P8: EVELIO GARCIA - SANTANDER | Q8: MAYORISTA INDUSTRIAL | R8: =E8/$E$2034 -> 0.018346153
A9: 1023 | B9: 759311128 | C9: 933426.82 | D9: HOLCIM COLOMBIA S.A | E9: 7.583777e+08 | F9: 1.4409176e+08 | G9: 17812192 | H9: 20305899 | I9: 0 | J9: 38118091 | K9: 8.6435137e+08 | L9: 86000980800 | M9: 860009808-5 | N9: BOGOTA - BOGOTA | O9: GRANDES CUENTAS | P9: GRANDES CUENTAS | Q9: MAYORISTA INDUSTRIAL | R9: =E9/$E$2034 -> 0.015106826
A10: 1246 | B10: 6.5493795e+08 | C10: 22842515 | D10: M SIERRA FERRETEROS S.A.S "TIENDA BLER CENTRO" | E10: 6.3209543e+08 | F10: 1.2009813e+08 | G10: 15602633 | H10: 0 | I10: 0 | J10: 15602633 | K10: 736590933 | L10: 90134981301 | M10: 901349813-9 | N10: BOGOTA - BOGOTA | O10: GRANDES CUENTAS | P10: GRANDES CUENTAS | Q10: MAYORISTA INDUSTRIAL | R10: =E10/$E$2034 -> 0.012591293
A11: 385 | B11: 552274178 | C11: 1871664.2 | D11: CONSTRULAR S.A.S. | E11: 5.5040251e+08 | F11: 0 | G11: 11500856 | H11: 0 | I11: 0 | J11: 11500856 | K11: 5.3890166e+08 | L11: 90046116100 | M11: 900461161-1 | N11: LETICIA - AMAZONAS | O11: INSTITUCIONAL | P11: INSTITUCIONAL | Q11: GRAN DISTRIBUIDOR | R11: =E11/$E$2034 -> 0.010963976
A12: 1841 | B12: 502582007 | C12: 461122.2 | D12: SIDOC S.A.S. "YUMBO" | E12: 5.0212088e+08 | F12: 95402968 | G12: 11277482 | H12: 8128134.3 | I12: 0 | J12: 19405616 | K12: 5.7811824e+08 | L12: 89033302300 | M12: 890333023-8 | N12: YUMBO - VALLE DEL CAUCA | O12: JORGE CASTRO - VALLE DE CAUCA | P12: JORGE CASTRO - VALLE DE CAUCA | Q12: GRAN DISTRIBUIDOR | R12: =E12/$E$2034 -> 0.01000221
A13: 1700 | B13: 5.1770995e+08 | C13: 44609328 | D13: ROBAYO RAUL/DISTRIBUCIONES ROBAYO | E13: 4.7310062e+08 | F13: 89889118 | G13: 0 | H13: 0 | I13: 0 | J13: 0 | K13: 5.6298974e+08 | L13: 7954332100 | M13: 79294188-4 | N13: BOGOTA - BOGOTA | O13: GRANDES CUENTAS | P13: GRANDES CUENTAS | Q13: MAYORISTA INDUSTRIAL | R13: =E13/$E$2034 -> 0.0094241282
... A1060: 370 | B1060: 3852777 | C1060: 0 | D1060: CONSORCIO ALTO RENDIMIENTO IF | E1060: 3852777 | F1060: 712077.63 | G1060: 43849.12 | H1060: 0 | I1060: 0 | J1060: 43849.12 | K1060: 4521005.5 | L1060: 90167456600 | M1060: 901674566-7 | N1060: BOGOTA - BOGOTA | O1060: INSTITUCIONAL | P1060: INSTITUCIONAL | Q1060: INDUSTRIAL 2 | R1060: =E1060/$E$2034 -> 7.6747024e-05
A1061: 1309 | B1061: 3846874 | C1061: 0 | D1061: METAL CARGO SAS | E1061: 3846874 | F1061: 730906.06 | G1061: 80516 | H1061: 0 | I1061: 0 | J1061: 80516 | K1061: 4497264.1 | L1061: 90029319400 | M1061: 900293194-1 | O1061: INDUSTRIAL | P1061: INDUSTRIAL | Q1061: PVP | R1061: =E1061/$E$2034 -> 7.6629436e-05
A1062: 1948 | B1062: 3841040 | C1062: 0 | D1062: TU CASITA DE PINTURAS S EN C | E1062: 3841040 | F1062: 729797.6 | G1062: 96026 | H1062: 0 | I1062: 0 | J1062: 96026 | K1062: 4474811.6 | L1062: 90088842200 | M1062: 900888422-0 | N1062: GIRARDOT - CUNDINAMARCA | O1062: OMAR MONTAÑA -SUR TOLIMA | P1062: OMAR MONTAÑA -SUR TOLIMA | Q1062: DISTRIBUIDOR | R1062: =E1062/$E$2034 -> 7.6513223e-05
A1063: 1302 | B1063: 3836962 | C1063: 0 | D1063: MELO MUETE ALBA MERCEDES/LEO PINTURAS | E1063: 3836962 | F1063: 729022.78 | G1063: 0 | H1063: 0 | I1063: 0 | J1063: 0 | K1063: 4565984.8 | L1063: 3975698300 | M1063: 39756983-1 | N1063: BOGOTA - BOGOTA | O1063: DIANA ARENAS - LOCALIDAD FONTIBON | P1063: DIANA ARENAS - LOCALIDAD FONTIBON | Q1063: DISTRIBUIDOR | R1063: =E1063/$E$2034 -> 7.643199e-05
A1064: 806 | B1064: 3836270 | C1064: 0 | D1064: G Y J FERRETERIAS S.A. - BARRANQUILLA | E1064: 3836270 | F1064: 728891.3 | G1064: 79132.75 | H1064: 109333.7 | I1064: 0 | J1064: 188466.45 | K1064: 4376694.8 | L1064: 80013042608 | M1064: 800130426-3 | N1064: BARRANQUILLA - ATLANTICO | O1064: CRISTIAN BETANCOURT - COSTA ATLANTICA CENTRO | P1064: CRISTIAN BETANCOURT - COSTA ATLANTICA CENTRO | Q1064: GRAN DISTRIBUIDOR | R1064: =E1064/$E$2034 -> 7.6418205e-05
A1065: 379 | B1065: 3831228 | C1065: 0 | D1065: CONSTRUDISEÑOS INGENIERIA S.A.S | E1065: 3831228 | F1065: 727933.32 | G1065: 95780.7 | H1065: 0 | I1065: 0 | J1065: 95780.7 | K1065: 4463380.6 | L1065: 90104049400 | M1065: 901040494-4 | N1065: TURBACO - BOLIVAR | O1065: CRISTIAN BETANCOURT - COSTA ATLANTICA CENTRO | P1065: CRISTIAN BETANCOURT - COSTA ATLANTICA CENTRO | Q1065: DISTRIBUIDOR | R1065: =E1065/$E$2034 -> 7.6317769e-05
A1066: 1180 | B1066: 3828332 | C1066: 0 | D1066: LA PERLA DEL COLOR S.A.S. | E1066: 3828332 | F1066: 727383.08 | G1066: 82553.15 | H1066: 0 | I1066: 0 | J1066: 82553.15 | K1066: 4473161.9 | L1066: 90111827700 | M1066: 901118277-1 | N1066: BOGOTA - BOGOTA | O1066: ALFONSO ALBA - LOCALIDAD USAQUEN | P1066: ALFONSO ALBA - LOCALIDAD USAQUEN | Q1066: DISTRIBUIDOR | R1066: =E1066/$E$2034 -> 7.6260081e-05
A1067: 1385 | B1067: 3825636 | C1067: 0 | D1067: MUNDIAL DE DOBLECES S.A.S "PRINCIPAL" | E1067: 3825636 | F1067: 726870.84 | G1067: 34770.52 | H1067: 0 | I1067: 0 | J1067: 34770.52 | K1067: 4517736.3 | L1067: 83008067500 | M1067: 830080675-4 | N1067: BOGOTA - BOGOTA | O1067: ALEJANDRO CARANTON -LOCALIDAD KENNEDY | P1067: ALEJANDRO CARANTON -LOCALIDAD KENNEDY | Q1067: DISTRIBUIDOR | R1067: =E1067/$E$2034 -> 7.6206377e-05
A1068: 1449 | B1068: 3811544 | C1068: 0 | D1068: ORDOÑEZ MENESES LUZ ELIANY / UNIACABADOS QUILICHAO | E1068: 3811544 | F1068: 724193.36 | G1068: 0 | H1068: 0 | I1068: 0 | J1068: 0 | K1068: 4535737.4 | L1068: 114407078000 | M1068: 1144070780-1 | N1068: SANTANDER DE QUILICHAO - CAUCA | O1068: JORGE CASTRO - CAUCA | P1068: JORGE CASTRO - CAUCA | Q1068: DISTRIBUIDOR | R1068: =E1068/$E$2034 -> 7.5925665e-05
A1069: 697 | B1069: 3809224 | C1069: 0 | D1069: FERRETERIA LOS FIERROS S.A.S "CDS BELLO" | E1069: 3809224 | F1069: 723752.56 | G1069: 41391.95 | H1069: 0 | I1069: 0 | J1069: 41391.95 | K1069: 4491584.6 | L1069: 81101242714 | M1069: 811012427-5 | N1069: BELLO - ANTIOQUIA | O1069: ANTIOQUIA | P1069: ANTIOQUIA | Q1069: GRAN DISTRIBUIDOR | R1069: =E1069/$E$2034 -> 7.5879451e-05
A1070: 1707 | B1070: 3788559 | C1070: 8542.35 | D1070: RODRIGUEZ BERNAL ORLANDO | E1070: 3780016.6 | F1070: 718203.16 | G1070: 0 | H1070: 0 | I1070: 0 | J1070: 0 | K1070: 4498219.8 | L1070: 7920538200 | M1070: 79205382-7 | N1070: SOACHA - CUNDINAMARCA | O1070: ALEJANDRO CARANTON -SOACHA - SIBATE | P1070: ALEJANDRO CARANTON -SOACHA - SIBATE | Q1070: DISTRIBUIDOR | R1070: =E1070/$E$2034 -> 7.5297643e-05
A1071: 1589 | B1071: 3786444 | C1071: 25057.08 | D1071: PINZON CARDENAS JAIME ERNESTO / PINTAPINTOR | E1071: 3761386.9 | F1071: 714663.51 | G1071: 0 | H1071: 0 | I1071: 0 | J1071: 0 | K1071: 4476050.4 | L1071: 1018478826 | M1071: 1018478826 | N1071: BOGOTA - BOGOTA | O1071: ALFONSO ALBA - LOCALIDAD SUBA | P1071: ALFONSO ALBA - LOCALIDAD SUBA | Q1071: DISTRIBUIDOR | R1071: =E1071/$E$2034 -> 7.492654e-05
A1072: 713 | B1072: 3757486 | C1072: 0 | D1072: FERRETERIA LUIS PENAGOS SAS | E1072: 3757486 | F1072: 713922.34 | G1072: 36984.8 | H1072: 0 | I1072: 0 | J1072: 36984.8 | K1072: 4434423.5 | L1072: 83003703900 | M1072: 830037039-8 | N1072: BOGOTA - BOGOTA | O1072: INDUSTRIAL | P1072: NORMA AGUILAR - LOCALIDAD MARTIRES | Q1072: DISTRIBUIDOR | R1072: =E1072/$E$2034 -> 7.4848834e-05
A1073: 488 | B1073: 3750744 | C1073: 0 | D1073: DIAZ PAREDES LUISA MARIA/ALMACEN DE PINTURAS D D & G | E1073: 3750744 | F1073: 712641.36 | G1073: 0 | H1073: 0 | I1073: 0 | J1073: 0 | K1073: 4463385.4 | L1073: 4170481100 | M1073: 41704811-7 | N1073: BOGOTA - BOGOTA | O1073: ALEJANDRO CARANTON -LOCALIDAD ANTONIO NARIÑO | P1073: ALEJANDRO CARANTON -LOCALIDAD ANTONIO NARIÑO | Q1073: DISTRIBUIDOR | R1073: =E1073/$E$2034 -> 7.4714534e-05
... A1362: 1808 | B1362: 1289030 | C1362: 0 | D1362: SANDOVAL CARDOZO JAIRO/FERRELECTRICOS J.S. 54 | E1362: 1289030 | F1362: 244915.7 | G1362: 0 | H1362: 0 | I1362: 0 | J1362: 0 | K1362: 1533945.7 | L1362: 1938253400 | M1362: 19382534-4 | N1362: BOGOTA - BOGOTA | O1362: DIANA ARENAS - LOCALIDAD CHAPINERO | P1362: DIANA ARENAS - LOCALIDAD CHAPINERO | Q1362: DISTRIBUIDOR | R1362: =E1362/$E$2034 -> 2.5677379e-05
A1363: 1456 | B1363: 1285234 | C1363: 0 | D1363: ORJUELA CAMPO MIGUEL | E1363: 1285234 | F1363: 244194.46 | G1363: 0 | H1363: 0 | I1363: 0 | J1363: 0 | K1363: 1529428.5 | L1363: 1718506500 | M1363: 17185065-4 | O1363: MOSTRADOR | P1363: MOSTRADOR | Q1363: PVP | R1363: =E1363/$E$2034 -> 2.5601763e-05
A1364: 963 | B1364: 1269882 | C1364: 0 | D1364: HELVER YESID GONZALEZ PUENTES | E1364: 1269882 | F1364: 241277.58 | G1364: 0 | H1364: 0 | I1364: 0 | J1364: 0 | K1364: 1511159.6 | L1364: 107372205500 | M1364: 1073722055-1 | N1364: BOGOTA - BOGOTA | O1364: TUL SAS | P1364: TUL SAS | Q1364: DISTRIBUIDOR | R1364: =E1364/$E$2034 -> 2.5295952e-05
A1365: 1424 | B1365: 1265228 | C1365: 0 | D1365: OBRACOL SAS CONSTRUCTORA | E1365: 1265228 | F1365: 240393.32 | G1365: 31630.7 | H1365: 0 | I1365: 0 | J1365: 31630.7 | K1365: 1473990.6 | L1365: 90039484800 | M1365: 900394848-3 | N1365: BOGOTA - BOGOTA | O1365: INSTITUCIONAL | P1365: INSTITUCIONAL | Q1365: INDUSTRIAL 2 | R1365: =E1365/$E$2034 -> 2.5203245e-05
A1366: 253 | B1366: 1259429 | C1366: 0 | D1366: CASTAÑEDA GRANADOS JUAN CARLOS / CONSORCIO FERRELECTRICOS | E1366: 1259429 | F1366: 239291.51 | G1366: 0 | H1366: 0 | I1366: 0 | J1366: 0 | K1366: 1498720.5 | L1366: 424575800 | M1366: 4245758-0 | N1366: BOGOTA - BOGOTA | O1366: ALFONSO ALBA - LOCALIDAD USAQUEN | P1366: ALFONSO ALBA - LOCALIDAD USAQUEN | Q1366: DISTRIBUIDOR | R1366: =E1366/$E$2034 -> 2.5087729e-05
A1367: 978 | B1367: 1234768 | C1367: 0 | D1367: HERNANDEZ PEÑA DIANA MARLEN / FERRELECTRICOS LA PALMITA DH | E1367: 1234768 | F1367: 234605.92 | G1367: 0 | H1367: 0 | I1367: 0 | J1367: 0 | K1367: 1469373.9 | L1367: 3519949600 | M1367: 35199496-1 | N1367: PACHO - CUNDINAMARCA | O1367: OMAR MONTAÑA - SABANA CENTRO | P1367: INACTIVO | Q1367: DISTRIBUIDOR | R1367: =E1367/$E$2034 -> 2.4596484e-05
A1368: 680 | B1368: 1227205 | C1368: 0 | D1368: FERRETERIA FM S.A.S. | E1368: 1227205 | F1368: 233168.95 | G1368: 0 | H1368: 0 | I1368: 0 | J1368: 0 | K1368: 1460373.9 | L1368: 90099463500 | M1368: 900994635-6 | N1368: BOGOTA - BOGOTA | O1368: ALFONSO ALBA - LOCALIDAD ENGATIVA | P1368: ALFONSO ALBA - LOCALIDAD ENGATIVA | Q1368: DISTRIBUIDOR | R1368: =E1368/$E$2034 -> 2.444583e-05
A1369: 1711 | B1369: 1217656 | C1369: 0 | D1369: RODRIGUEZ CASTRO JORGE ALVEIRO / FERREPINTURAS JR | E1369: 1217656 | F1369: 231354.64 | G1369: 0 | H1369: 0 | I1369: 0 | J1369: 0 | K1369: 1449010.6 | L1369: 409730900 | M1369: 4097309-1 | N1369: CHIQUINQUIRA - BOYACA | O1369: WILSON SEPULVEDA - BOYACA | P1369: WILSON SEPULVEDA - BOYACA | Q1369: DISTRIBUIDOR | R1369: =E1369/$E$2034 -> 2.4255615e-05
A1370: 1912 | B1370: 1216215 | C1370: 0 | D1370: THE OFICCE STORE SAS | E1370: 1216215 | F1370: 231080.85 | G1370: 0 | H1370: 0 | I1370: 0 | J1370: 0 | K1370: 1447295.9 | L1370: 90105541200 | M1370: 901055412-6 | N1370: BOGOTA - BOGOTA | O1370: DIANA ARENAS - LOCALIDAD BARRIOS UNIDOS | P1370: DIANA ARENAS - LOCALIDAD BARRIOS UNIDOS | Q1370: DISTRIBUIDOR | R1370: =E1370/$E$2034 -> 2.422691e-05
A1371: 647 | B1371: 1205363 | C1371: 0 | D1371: FERRELECTRICOS EL OASIS SAS | E1371: 1205363 | F1371: 229018.97 | G1371: 0 | H1371: 0 | I1371: 0 | J1371: 0 | K1371: 1434382 | L1371: 90169914300 | M1371: 901699143-3 | N1371: BOGOTA - BOGOTA | O1371: ALEJANDRO CARANTON -LOCALIDAD ANTONIO NARIÑO | P1371: ALEJANDRO CARANTON -LOCALIDAD ANTONIO NARIÑO | Q1371: DISTRIBUIDOR | R1371: =E1371/$E$2034 -> 2.4010739e-05
A1372: 158 | B1372: 1204596 | C1372: 0 | D1372: BENAVIDES BUITRAGO MARYOLY/FERRELECTRICOS LA 15 | E1372: 1204596 | F1372: 228873.24 | G1372: 0 | H1372: 0 | I1372: 0 | J1372: 0 | K1372: 1433469.2 | L1372: 5239619300 | M1372: 52396193-1 | N1372: MOSQUERA - CUNDINAMARCA | O1372: DIANA ARENAS - SABANA OCCIDENTE | P1372: DIANA ARENAS - SABANA OCCIDENTE | Q1372: DISTRIBUIDOR | R1372: =E1372/$E$2034 -> 2.399546e-05
A1373: 1667 | B1373: 1203795.2 | C1373: 0 | D1373: RETAMBORES BOGOTA S A S | E1373: 1203795.2 | F1373: 228721.1 | G1373: 0 | H1373: 0 | I1373: 0 | J1373: 0 | K1373: 1432516.3 | L1373: 90128924700 | M1373: 901289247-1 | N1373: SOACHA - CUNDINAMARCA | O1373: MOSTRADOR | P1373: MOSTRADOR | Q1373: PVP | R1373: =E1373/$E$2034 -> 2.3979509e-05
A1374: 952 | B1374: 1194242 | C1374: 0 | D1374: GUTIERREZ SAAVEDRA MAYERLLYS / PINTUELECTRICOS M Y M | E1374: 1194242 | F1374: 226905.98 | G1374: 0 | H1374: 0 | I1374: 0 | J1374: 0 | K1374: 1421148 | L1374: 102237509800 | M1374: 1022375098-1 | N1374: PAIPA - BOYACA | O1374: WILSON SEPULVEDA - BOYACA | P1374: WILSON SEPULVEDA - BOYACA | Q1374: DISTRIBUIDOR | R1374: =E1374/$E$2034 -> 2.3789209e-05
A1375: 1731 | B1375: 1175110 | C1375: 0 | D1375: RODRIGUEZ SAAVEDRA DENNIS ANYELID | E1375: 1175110 | F1375: 223270.9 | G1375: 0 | H1375: 0 | I1375: 0 | J1375: 0 | K1375: 1398380.9 | L1375: 2402341400 | M1375: 24023414-2 | N1375: BOGOTA - BOGOTA | O1375: NORMA AGUILAR - LOCALIDAD USME | P1375: NORMA AGUILAR - LOCALIDAD USME | Q1375: DISTRIBUIDOR | R1375: =E1375/$E$2034 -> 2.3408101e-05
... A1533: 504 | B1533: 401950 | C1533: 0 | D1533: DISTRI MATERIALES LA UNION S.A.S. | E1533: 401950 | F1533: 76370.5 | G1533: 0 | H1533: 0 | I1533: 0 | J1533: 0 | K1533: 478320.5 | L1533: 90057246300 | M1533: 900572463-5 | N1533: BOGOTA - BOGOTA | O1533: ALEJANDRO CARANTON -LOCALIDAD KENNEDY | P1533: ALEJANDRO CARANTON -LOCALIDAD KENNEDY | Q1533: DISTRIBUIDOR | R1533: =E1533/$E$2034 -> 8.0068133e-06
A1534: 1498 | B1534: 400877 | C1534: 0 | D1534: PAEZ QUITO FABIO GUILLERMO | E1534: 400877 | F1534: 76166.63 | G1534: 0 | H1534: 0 | I1534: 0 | J1534: 0 | K1534: 477043.63 | L1534: 8017211900 | M1534: 80172119 | O1534: EMPLEADO | P1534: EMPLEADO | Q1534: INDUSTRIAL 2 | R1534: =E1534/$E$2034 -> 7.9854392e-06
A1535: 888 | B1535: 393523 | C1535: 0 | D1535: GOMEZ JOYA FABIO HERNAN / FERRELECTRICOS HG LA 56 | E1535: 393523 | F1535: 74769.37 | G1535: 0 | H1535: 0 | I1535: 0 | J1535: 0 | K1535: 468292.37 | L1535: 7999837300 | M1535: 79998373-2 | N1535: BOGOTA - BOGOTA | O1535: ALEJANDRO CARANTON -LOCALIDAD BOSA | P1535: ALEJANDRO CARANTON -LOCALIDAD BOSA | Q1535: DISTRIBUIDOR | R1535: =E1535/$E$2034 -> 7.8389481e-06
A1536: 1855 | B1536: 389628 | C1536: 0 | D1536: SILVA AREVALO ROSALBA/FERRELECTRICOS LOS MELLIS | E1536: 389628 | F1536: 74029.32 | G1536: 0 | H1536: 0 | I1536: 0 | J1536: 0 | K1536: 463657.32 | L1536: 5262420300 | M1536: 52624203-6 | N1536: BOGOTA - BOGOTA | O1536: ALFONSO ALBA - LOCALIDAD ENGATIVA | P1536: ALFONSO ALBA - LOCALIDAD ENGATIVA | Q1536: DISTRIBUIDOR | R1536: =E1536/$E$2034 -> 7.76136e-06
A1537: 1504 | B1537: 389406 | C1537: 0 | D1537: PANIAGUA JARA ANGELA | E1537: 389406 | F1537: 73987.14 | G1537: 0 | H1537: 0 | I1537: 0 | J1537: 0 | K1537: 463393.14 | L1537: 101905389200 | M1537: 1019053892 | N1537: BOGOTA - BOGOTA | O1537: EMPLEADO | P1537: EMPLEADO | Q1537: INDUSTRIAL 2 | R1537: =E1537/$E$2034 -> 7.7569378e-06
A1538: 869 | B1538: 385654.38 | C1538: 0 | D1538: GEOVANNY ARCINIEGAS GARCIA | E1538: 385654.38 | F1538: 72324.33 | G1538: 0 | H1538: 0 | I1538: 0 | J1538: 0 | K1538: 457978.71 | L1538: 7995352700 | M1538: 79953527-6 | N1538: BOGOTA - BOGOTA | O1538: MOSTRADOR | P1538: MOSTRADOR | Q1538: PVP | R1538: =E1538/$E$2034 -> 7.6822058e-06
A1539: 1133 | B1539: 384096 | C1539: 0 | D1539: JOSE EDILSO CASTRO RIAÑO | E1539: 384096 | F1539: 72978.24 | G1539: 0 | H1539: 0 | I1539: 0 | J1539: 0 | K1539: 457074.24 | L1539: 103241258500 | M1539: 1032412585-2 | N1539: BOGOTA - BOGOTA | O1539: TUL SAS | P1539: TUL SAS | Q1539: DISTRIBUIDOR | R1539: =E1539/$E$2034 -> 7.651163e-06
A1540: 49 | B1540: 375079 | C1540: 0 | D1540: AGRUPACION VILLA SANTORINI - PROPIEDAD HORIZONTAL | E1540: 375079 | F1540: 70315.01 | G1540: 0 | H1540: 0 | I1540: 0 | J1540: 0 | K1540: 445394.01 | L1540: 90036285700 | M1540: 900362857-2 | N1540: BOGOTA - BOGOTA | O1540: MOSTRADOR | P1540: MOSTRADOR | Q1540: PVP | R1540: =E1540/$E$2034 -> 7.471545e-06
A1541: 979 | B1541: 367138 | C1541: 0 | D1541: HERNANDEZ RODRIGUEZ LADY DANIELA / FERREPINTURAS TECNIKOLOR | E1541: 367138 | F1541: 69756.22 | G1541: 0 | H1541: 0 | I1541: 0 | J1541: 0 | K1541: 436894.22 | L1541: 101845816400 | M1541: 1018458164-2 | N1541: BOGOTA - BOGOTA | O1541: DIANA ARENAS - LOCALIDAD BARRIOS UNIDOS | P1541: DIANA ARENAS - LOCALIDAD BARRIOS UNIDOS | Q1541: DISTRIBUIDOR | R1541: =E1541/$E$2034 -> 7.3133609e-06
A1542: 500 | B1542: 366879 | C1542: 0 | D1542: DISEÑO,CONSTRUCCION E INGENERIA LFG SAS | E1542: 366879 | F1542: 69707.01 | G1542: 9171.98 | H1542: 0 | I1542: 0 | J1542: 9171.98 | K1542: 427414.03 | L1542: 90121129800 | M1542: 901211298-1 | N1542: BOGOTA - BOGOTA | O1542: OFICINA | P1542: OFICINA | Q1542: INDUSTRIAL 3 | R1542: =E1542/$E$2034 -> 7.3082017e-06
A1543: 1043 | B1543: 363707.49 | C1543: 0 | D1543: IMCD COLOMBIA S.A.S | E1543: 363707.49 | F1543: 69104.42 | G1543: 0 | H1543: 0 | I1543: 0 | J1543: 0 | K1543: 432811.91 | L1543: 80013459700 | M1543: 800134597-2 | N1543: BOGOTA - BOGOTA | O1543: MOSTRADOR | P1543: MOSTRADOR | Q1543: PVP | R1543: =E1543/$E$2034 -> 7.2450254e-06
A1544: 1512 | B1544: 363468 | C1544: 0 | D1544: PARDO PINZON CARLOS ALBERTO / FERRIPARS | E1544: 363468 | F1544: 69058.92 | G1544: 0 | H1544: 0 | I1544: 0 | J1544: 0 | K1544: 432526.92 | L1544: 8001792300 | M1544: 80017923-9 | N1544: BOGOTA - BOGOTA | O1544: ALFONSO ALBA - LOCALIDAD ENGATIVA | P1544: ALFONSO ALBA - LOCALIDAD ENGATIVA | Q1544: DISTRIBUIDOR | R1544: =E1544/$E$2034 -> 7.2402548e-06
A1545: 1705 | B1545: 357311 | C1545: 0 | D1545: RODOLFO EUCLIDES YARURO PICON | E1545: 357311 | F1545: 67889.09 | G1545: 0 | H1545: 0 | I1545: 0 | J1545: 0 | K1545: 425200.09 | L1545: 7967974700 | M1545: 79679747-5 | N1545: BOGOTA - BOGOTA | O1545: TUL SAS | P1545: TUL SAS | Q1545: DISTRIBUIDOR | R1545: =E1545/$E$2034 -> 7.1176078e-06
A1546: 1137 | B1546: 354737 | C1546: 0 | D1546: JOSE WILLIAM RUIZ RAMIREZ | E1546: 354737 | F1546: 67400.03 | G1546: 0 | H1546: 0 | I1546: 0 | J1546: 0 | K1546: 422137.03 | L1546: 113688838300 | M1546: 1136888383 | N1546: BOGOTA - BOGOTA | O1546: EMPLEADO | P1546: EMPLEADO | Q1546: INDUSTRIAL 2 | R1546: =E1546/$E$2034 -> 7.0663339e-06
... A1745: 1242 | B1745: 52158 | C1745: 0 | D1745: LUIS LOZANO | E1745: 52158 | F1745: 8960.02 | G1745: 0 | H1745: 0 | I1745: 0 | J1745: 0 | K1745: 61118.02 | L1745: 8090131000 | M1745: 80901310 | N1745: BOGOTA - BOGOTA | O1745: MOSTRADOR | P1745: MOSTRADOR | Q1745: PVP | R1745: =E1745/$E$2034 -> 1.0389834e-06
A1746: 495 | B1746: 50364 | C1746: 0 | D1746: DIEGO ARMANADO BAEZ LOPEZ | E1746: 50364 | F1746: 7289.16 | G1746: 0 | H1746: 0 | I1746: 0 | J1746: 0 | K1746: 57653.16 | L1746: 8017248400 | M1746: 80172484-1 | O1746: TUL SAS | P1746: TUL SAS | Q1746: DISTRIBUIDOR | R1746: =E1746/$E$2034 -> 1.003247e-06
A1747: 583 | B1747: 45672 | C1747: 0 | D1747: ERNESTO MARCUCCI PEREIRA | E1747: 45672 | F1747: 7727.68 | G1747: 0 | H1747: 0 | I1747: 0 | J1747: 0 | K1747: 53399.68 | L1747: 1926919200 | M1747: 19269192-0 | N1747: BOGOTA - BOGOTA | O1747: MOSTRADOR | P1747: MOSTRADOR | Q1747: PVP | R1747: =E1747/$E$2034 -> 9.0978275e-07
A1748: 234 | B1748: 38100 | C1748: 0 | D1748: CARLOS FERNANDO PADILLA USEDA | E1748: 38100 | F1748: 6289 | G1748: 0 | H1748: 0 | I1748: 0 | J1748: 0 | K1748: 44389 | L1748: 9129398100 | M1748: 91293981-8 | N1748: BOGOTA - BOGOTA | O1748: MOSTRADOR | P1748: MOSTRADOR | Q1748: PVP | R1748: =E1748/$E$2034 -> 7.5894909e-07
A1749: 90 | B1749: 37856 | C1749: 0 | D1749: AMED ANTENOR ABASOLO URRESTA | E1749: 37856 | F1749: 6242.64 | G1749: 0 | H1749: 0 | I1749: 0 | J1749: 0 | K1749: 44098.64 | L1749: 7954320100 | M1749: 79543201-1 | N1749: BOGOTA - BOGOTA | O1749: MOSTRADOR | P1749: MOSTRADOR | Q1749: PVP | R1749: =E1749/$E$2034 -> 7.5408863e-07
A1750: 1301 | B1750: 34093 | C1750: 0 | D1750: MELO MIGUEL | E1750: 34093 | F1750: 6477.67 | G1750: 0 | H1750: 0 | I1750: 0 | J1750: 0 | K1750: 40570.67 | L1750: 7921211500 | M1750: 79212115 | N1750: BOGOTA - BOGOTA | O1750: EMPLEADO | P1750: EMPLEADO | Q1750: INDUSTRIAL 2 | R1750: =E1750/$E$2034 -> 6.7912996e-07
A1751: 1033 | B1751: 32058 | C1751: 0 | D1751: HUGO ALBERTO ACERO MARTINEZ | E1751: 32058 | F1751: 5141.02 | G1751: 0 | H1751: 0 | I1751: 0 | J1751: 0 | K1751: 37199.02 | L1751: 8021061000 | M1751: 80210610-5 | N1751: BOGOTA - BOGOTA | O1751: MOSTRADOR | P1751: MOSTRADOR | Q1751: PVP | R1751: =E1751/$E$2034 -> 6.3859291e-07
A1752: 1516 | B1752: 31486.95 | C1752: 0 | D1752: PARRA OSORIO NELLY LUCIA | E1752: 31486.95 | F1752: 5032.52 | G1752: 0 | H1752: 0 | I1752: 0 | J1752: 0 | K1752: 36519.47 | L1752: 5249435000 | M1752: 52494350-1 | N1752: BOGOTA - BOGOTA | O1752: MOSTRADOR | P1752: MOSTRADOR | Q1752: PVP | R1752: =E1752/$E$2034 -> 6.2721764e-07
A1753: 2022 | B1753: 29454 | C1753: 0 | D1753: YURY VANESA ORTIZ GAVIRIA | E1753: 29454 | F1753: 4646.26 | G1753: 0 | H1753: 0 | I1753: 0 | J1753: 0 | K1753: 34100.26 | L1753: 100444298900 | M1753: 1004442989 | N1753: BOGOTA - BOGOTA | O1753: MOSTRADOR | P1753: MOSTRADOR | Q1753: PVP | R1753: =E1753/$E$2034 -> 5.8672143e-07
A1754: 549 | B1754: 22983 | C1754: 0 | D1754: EDGAR OSWALDO SERRANO ARCINIEGAS | E1754: 22983 | F1754: 3416.77 | G1754: 0 | H1754: 0 | I1754: 0 | J1754: 0 | K1754: 26399.77 | L1754: 1131296000 | M1754: 11312960-5 | N1754: BOGOTA - BOGOTA | O1754: MOSTRADOR | P1754: MOSTRADOR | Q1754: PVP | R1754: =E1754/$E$2034 -> 4.578196e-07
A1755: 1860 | B1755: 20769.94 | C1755: 0 | D1755: SIMON SERRANO VIDAL | E1755: 20769.94 | F1755: 2996.29 | G1755: 0 | H1755: 0 | I1755: 0 | J1755: 0 | K1755: 23766.23 | L1755: 101908357800 | M1755: 1019083578-0 | N1755: BOGOTA - BOGOTA | O1755: MOSTRADOR | P1755: MOSTRADOR | Q1755: PVP | R1755: =E1755/$E$2034 -> 4.1373562e-07
A1756: 552 | B1756: 18697 | C1756: 0 | D1756: EDUARDO EMILIO TRIANA RAMIREZ | E1756: 18697 | F1756: 2602.43 | G1756: 0 | H1756: 0 | I1756: 0 | J1756: 0 | K1756: 21299.43 | L1756: 7927784100 | M1756: 79277841-4 | N1756: BOGOTA - BOGOTA | O1756: MOSTRADOR | P1756: MOSTRADOR | Q1756: PVP | R1756: =E1756/$E$2034 -> 3.7244281e-07
A1757: 1715 | B1757: 12953 | C1757: 0 | D1757: RODRIGUEZ DANI | E1757: 12953 | F1757: 2461.07 | G1757: 0 | H1757: 0 | I1757: 0 | J1757: 0 | K1757: 15414.07 | L1757: 102080809500 | M1757: 1020808095 | O1757: EMPLEADO | P1757: EMPLEADO | Q1757: INDUSTRIAL 2
A1758: 968 | B1758: 12501 | C1758: 0 | D1758: HERNANDEZ BACCA HECTOR DANIEL | E1758: 12501 | F1758: 2375.19 | G1758: 0 | H1758: 0 | I1758: 0 | J1758: 0 | K1758: 14876.19 | L1758: 7960284000 | M1758: 79602840 | N1758: BOGOTA - BOGOTA | O1758: EMPLEADO | P1758: EMPLEADO | Q1758: INDUSTRIAL 2
A1759: 1202 | B1759: 8334 | C1759: 0 | D1759: LAURA VALENTINA URQUIJO | E1759: 8334 | F1759: 1583.46 | G1759: 0 | H1759: 0 | I1759: 0 | J1759: 0 | K1759: 9917.46 | L1759: 100356085900 | M1759: 1003560859 | N1759: BOGOTA - BOGOTA | O1759: EMPLEADO | P1759: EMPLEADO | Q1759: INDUSTRIAL 2
A1760: 4 | B1760: 0 | C1760: 0 | D1760: AAA HIERROS Y PERFILES HENAO S.A.S | E1760: 0 | F1760: 0 | G1760: 0 | H1760: 0 | I1760: 0 | J1760: 0 | K1760: 0 | L1760: 90072983700 | M1760: 900729837-2 | N1760: CALI - VALLE DEL CAUCA | O1760: JORGE CASTRO - VALLE DE CAUCA | P1760: JORGE CASTRO - VALLE DE CAUCA | Q1760: DISTRIBUIDOR
A1761: 6 | B1761: 0 | C1761: 0 | D1761: ACERARQ S.A.S. | E1761: 0 | F1761: 0 | G1761: 0 | H1761: 0 | I1761: 0 | J1761: 0 | K1761: 0 | L1761: 90012022000 | M1761: 900120220-3 | N1761: BOGOTA - BOGOTA | O1761: INDUSTRIAL | P1761: INDUSTRIAL | Q1761: INDUSTRIAL 2
A1762: 14 | B1762: 0 | C1762: 0 | D1762: ACOSTA JIMENEZ ERICK SEBASTIAN/DISTRIBUIDORA EL IMPERIO DE LAS PINTURAS | E1762: 0 | F1762: 0 | G1762: 0 | H1762: 0 | I1762: 0 | J1762: 0 | K1762: 0 | L1762: 100774195200 | M1762: 1007741952-2 | N1762: ACACIAS - META | O1762: WILSON SEPULVEDA - META | P1762: WILSON SEPULVEDA - META | Q1762: GRAN DISTRIBUIDOR
A1763: 15 | B1763: 0 | C1763: 0 | D1763: ADAN JOSE EMILIO | E1763: 0 | F1763: 0 | G1763: 0 | H1763: 0 | I1763: 0 | J1763: 0 | K1763: 0 | L1763: 111604154500 | M1763: 1116041545 | N1763: BOGOTA - BOGOTA | O1763: EMPLEADO | P1763: EMPLEADO | Q1763: INDUSTRIAL 2
A1764: 47 | B1764: 0 | C1764: 0 | D1764: AGROCONSTRUCCIONES SERVIMAT SANDOVAL S.A.S | E1764: 0 | F1764: 0 | G1764: 0 | H1764: 0 | I1764: 0 | J1764: 0 | K1764: 0 | L1764: 90004606700 | M1764: 900046067-6 | N1764: MOSQUERA - CUNDINAMARCA | O1764: DIANA ARENAS - SABANA OCCIDENTE | P1764: INACTIVO | Q1764: DISTRIBUIDOR
A1765: 48 | B1765: 0 | C1765: 0 | D1765: AGROSERVICIOS J J U SAS | E1765: 0 | F1765: 0 | G1765: 0 | H1765: 0 | I1765: 0 | J1765: 0 | K1765: 0 | L1765: 90063640200 | M1765: 900636402-2 | N1765: BOGOTA - BOGOTA | O1765: OMAR MONTAÑA - SABANA CENTRO | P1765: OMAR MONTAÑA - SABANA CENTRO | Q1765: DISTRIBUIDOR
A1766: 61 | B1766: 0 | C1766: 0 | D1766: ALBEIRO GALLEGO | E1766: 0 | F1766: 0 | G1766: 0 | H1766: 0 | I1766: 0 | J1766: 0 | K1766: 0 | L1766: 100236935400 | M1766: 1002369354 | N1766: BOGOTA - BOGOTA | O1766: EMPLEADO | P1766: EMPLEADO | Q1766: INDUSTRIAL 2
A1767: 70 | B1767: 0 | C1767: 0 | D1767: ALEXANDRA TORRES GARZÓN | E1767: 0 | F1767: 0 | G1767: 0 | H1767: 0 | I1767: 0 | J1767: 0 | K1767: 0 | L1767: 3526464200 | M1767: 35264642-9 | N1767: VILLAVICENCIO - META | O1767: MOSTRADOR | P1767: MOSTRADOR | Q1767: PVP
A1768: 74 | B1768: 0 | C1768: 0 | D1768: ALMA VP PROYECTOS S A S | E1768: 0 | F1768: 0 | G1768: 0 | H1768: 0 | I1768: 0 | J1768: 0 | K1768: 0 | L1768: 900077562000 | M1768: 900077562-3 | N1768: BOGOTA - BOGOTA | O1768: MOSTRADOR | P1768: MOSTRADOR | Q1768: INDUSTRIAL 1
A1769: 82 | B1769: 0 | C1769: 0 | D1769: ALVARADO PERDOMO FANNY/FERRETERIA UNIDO | E1769: 0 | F1769: 0 | G1769: 0 | H1769: 0 | I1769: 0 | J1769: 0 | K1769: 0 | L1769: 5511146900 | M1769: 55111469-7 | N1769: GIGANTE - HUILA | O1769: WILSON SEPULVEDA - HUILA - CAQUETA | P1769: WILSON SEPULVEDA - HUILA - CAQUETA | Q1769: DISTRIBUIDOR
... A1818: 386 | B1818: 0 | C1818: 0 | D1818: CONSTRUNORTE COMERCIALIZADORA S.A.S "SUC. BELLO HORIZONTE" | E1818: 0 | F1818: 0 | G1818: 0 | H1818: 0 | I1818: 0 | J1818: 0 | K1818: 0 | L1818: 90064823400 | M1818: 900648234-3 | N1818: POPAYAN - CAUCA | O1818: JORGE CASTRO - CAUCA | P1818: JORGE CASTRO - CAUCA | Q1818: DISTRIBUIDOR
A1819: 400 | B1819: 0 | C1819: 0 | D1819: CORTES PLATA JOAHO STIVEN | E1819: 0 | F1819: 0 | G1819: 0 | H1819: 0 | I1819: 0 | J1819: 0 | K1819: 0 | L1819: 103247879600 | M1819: 1032478796 | O1819: EMPLEADO | P1819: EMPLEADO | Q1819: INDUSTRIAL 2
A1820: 406 | B1820: 0 | C1820: 0 | D1820: CRUZ ORTEGA ZAMIR/ELECTRICOS Y FERRETERIA CRA 15 LOCAL 2 | E1820: 0 | F1820: 0 | G1820: 0 | H1820: 0 | I1820: 0 | J1820: 0 | K1820: 0 | L1820: 8002408300 | M1820: 80024083-6 | N1820: BOGOTA - BOGOTA | O1820: DIANA ARENAS - LOCALIDAD CHAPINERO | P1820: DIANA ARENAS - LOCALIDAD CHAPINERO | Q1820: DISTRIBUIDOR
A1821: 407 | B1821: 0 | C1821: 0 | D1821: CRUZ ROJA COLOMBIANA SECCIONAL CUNDINAMARCA Y BOGOTA D.C. | E1821: 0 | F1821: 0 | G1821: 0 | H1821: 0 | I1821: 0 | J1821: 0 | K1821: 0 | L1821: 86007030100 | M1821: 860070301-1 | N1821: BOGOTA - BOGOTA | O1821: INSTITUCIONAL | P1821: INSTITUCIONAL | Q1821: INDUSTRIAL 2
A1822: 408 | B1822: 0 | C1822: 0 | D1822: CS INDUMETALICAS S.A.S. | E1822: 0 | F1822: 0 | G1822: 0 | H1822: 0 | I1822: 0 | J1822: 0 | K1822: 0 | L1822: 90134467000 | M1822: 901344670-1 | N1822: BOGOTA - BOGOTA | O1822: MOSTRADOR | P1822: MOSTRADOR | Q1822: INDUSTRIAL 1
A1823: 409 | B1823: 0 | C1823: 0 | D1823: CUBIDES PARADA JINIER/PINTURAS LA MEZCLA PROFESIONAL DE COLORES | E1823: 0 | F1823: 0 | G1823: 0 | H1823: 0 | I1823: 0 | J1823: 0 | K1823: 0 | L1823: 5178064900 | M1823: 51780649-0 | N1823: BOGOTA - BOGOTA | O1823: ALFONSO ALBA - LOCALIDAD SUBA | P1823: ALFONSO ALBA - LOCALIDAD SUBA | Q1823: DISTRIBUIDOR
A1824: 436 | B1824: 0 | C1824: 0 | D1824: DANIEL RODOLFO BELEÑO MIRANDA | E1824: 0 | F1824: 0 | G1824: 0 | H1824: 0 | I1824: 0 | J1824: 0 | K1824: 0 | L1824: 105173478600 | M1824: 1051734786 | N1824: BOGOTA - BOGOTA | O1824: EMPLEADO | P1824: EMPLEADO | Q1824: INDUSTRIAL 2
A1825: 438 | B1825: 0 | C1825: 0 | D1825: DAVID GARZON RAMIREZ | E1825: 0 | F1825: 0 | G1825: 0 | H1825: 0 | I1825: 0 | J1825: 0 | K1825: 0 | L1825: 8018488200 | M1825: 80184882 | N1825: COTA - CUNDINAMARCA | O1825: EMPLEADO | P1825: EMPLEADO | Q1825: INDUSTRIAL 2
A1826: 442 | B1826: 0 | C1826: 0 | D1826: DAZA ISIDRO/DEPOSITO TUNA | E1826: 0 | F1826: 0 | G1826: 0 | H1826: 0 | I1826: 0 | J1826: 0 | K1826: 0 | L1826: 171960612 | M1826: 17196061-2 | N1826: BOGOTA - BOGOTA | O1826: OFICINA | P1826: OFICINA | Q1826: INDUSTRIAL 2
A1827: 450 | B1827: 0 | C1827: 0 | D1827: DEIVIS MANUEL MEJIA | E1827: 0 | F1827: 0 | G1827: 0 | H1827: 0 | I1827: 0 | J1827: 0 | K1827: 0 | L1827: 1103898300 | M1827: 11038983 | O1827: EMPLEADO | P1827: EMPLEADO | Q1827: INDUSTRIAL 2
A1828: 455 | B1828: 0 | C1828: 0 | D1828: DEPOSITO DE MADERAS Y MATERIALES EL PORVENIR | E1828: 0 | F1828: 0 | G1828: 0 | H1828: 0 | I1828: 0 | J1828: 0 | K1828: 0 | L1828: 90003283800 | M1828: 900032838-7 | N1828: BOGOTA - BOGOTA | O1828: ALEJANDRO CARANTON -LOCALIDAD ANTONIO NARIÑO | P1828: INACTIVO | Q1828: DISTRIBUIDOR
A1829: 462 | B1829: 0 | C1829: 0 | D1829: DEPOSITO JC GARAVITO S.A.S. | E1829: 0 | F1829: 0 | G1829: 0 | H1829: 0 | I1829: 0 | J1829: 0 | K1829: 0 | L1829: 90144441700 | M1829: 901444417-1 | N1829: VILLETA - CUNDINAMARCA | O1829: OMAR MONTAÑA - SABANA CENTRO | P1829: OMAR MONTAÑA - SABANA CENTRO | Q1829: DISTRIBUIDOR
A1830: 487 | B1830: 0 | C1830: 0 | D1830: DIAZ OSORIO YURI YESSENIA/LA ORNAMENTACION FERRETERIA | E1830: 0 | F1830: 0 | G1830: 0 | H1830: 0 | I1830: 0 | J1830: 0 | K1830: 0 | L1830: 101720455700 | M1830: 1017204557-1 | N1830: PUERTO BOYACA - BOYACA | O1830: OMAR MONTAÑA - NTE DEL TOLIMA | P1830: OMAR MONTAÑA - NTE DEL TOLIMA | Q1830: DISTRIBUIDOR
A1831: 494 | B1831: 0 | C1831: 0 | D1831: DIEGO ALEJANDRO CORREA GARZON | E1831: 0 | F1831: 0 | G1831: 0 | H1831: 0 | I1831: 0 | J1831: 0 | K1831: 0 | L1831: 8081718300 | M1831: 80817183 | N1831: BOGOTA - BOGOTA | O1831: EMPLEADO | P1831: EMPLEADO | Q1831: INDUSTRIAL 2
A1832: 498 | B1832: 0 | C1832: 0 | D1832: DIGITAL BUSINESS DBX LTDA | E1832: 0 | F1832: 0 | G1832: 0 | H1832: 0 | I1832: 0 | J1832: 0 | K1832: 0 | L1832: 90008434100 | M1832: 900084341-1 | N1832: BOGOTA - BOGOTA | O1832: OFICINA | P1832: OFICINA | Q1832: DISTRIBUIDOR
A1833: 508 | B1833: 0 | C1833: 0 | D1833: DISTRIBUCIONES FERRE - MAKRO S.A.S. | E1833: 0 | F1833: 0 | G1833: 0 | H1833: 0 | I1833: 0 | J1833: 0 | K1833: 0 | L1833: 90142605700 | M1833: 901426057-7 | N1833: BELEN - BOYACA | O1833: WILSON SEPULVEDA - BOYACA | P1833: WILSON SEPULVEDA - BOYACA | Q1833: DISTRIBUIDOR
A1834: 511 | B1834: 0 | C1834: 0 | D1834: DISTRIBUIDORA ALIANZA LTDA | E1834: 0 | F1834: 0 | G1834: 0 | H1834: 0 | I1834: 0 | J1834: 0 | K1834: 0 | L1834: 83005513700 | M1834: 830055137-8 | N1834: MOSQUERA - CUNDINAMARCA | O1834: NORMA AGUILAR - LOCALIDAD MARTIRES | P1834: NORMA AGUILAR - LOCALIDAD MARTIRES | Q1834: GRAN DISTRIBUIDOR
A1835: 519 | B1835: 0 | C1835: 0 | D1835: DISTRIBUIDORA ESPECIAL FERRETERA ESFERA S.A.S. | E1835: 0 | F1835: 0 | G1835: 0 | H1835: 0 | I1835: 0 | J1835: 0 | K1835: 0 | L1835: 90060397100 | M1835: 900603971-1 | N1835: BOGOTA - BOGOTA | O1835: ALEJANDRO CARANTON -LOCALIDAD RAFAEL URIBE URIBE | P1835: ALEJANDRO CARANTON -LOCALIDAD RAFAEL URIBE URIBE | Q1835: DISTRIBUIDOR
A1836: 550 | B1836: 0 | C1836: 0 | D1836: EDIFICIO ALMENAS DEL CASTILLO PROPIEDAD HORIZONTAL | E1836: 0 | F1836: 0 | G1836: 0 | H1836: 0 | I1836: 0 | J1836: 0 | K1836: 0 | L1836: 83004332200 | M1836: 830043322-2 | N1836: BOGOTA - BOGOTA | O1836: INSTITUCIONAL | P1836: INSTITUCIONAL | Q1836: INDUSTRIAL 2
A1837: 556 | B1837: 0 | C1837: 0 | D1837: EL COFRAL S.A.S | E1837: 0 | F1837: 0 | G1837: 0 | H1837: 0 | I1837: 0 | J1837: 0 | K1837: 0 | L1837: 90143155400 | M1837: 901431554-6 | N1837: EL BANCO - MAGDALENA | O1837: CRISTIAN BETANCOURT - COSTA ATLANTICA NORTE | P1837: CRISTIAN BETANCOURT - COSTA ATLANTICA NORTE | Q1837: DISTRIBUIDOR
...

Sheet 2025
A1: # | B1: Valor Bruto | C1: Descuento | D1: Nombre de cliente/proveedor | E1: Subtotal | F1: Impuesto | G1: ReteFuente | H1: Rete IVA | I1: Rete ICA | J1: Total Reteciones | K1: Total Documento | L1: Cod SN | M1: NIT | N1: City | O1: Vendedor en doc | P1: Vendedor Actual | Q1: Canal de Cliente | R1: PARTICIPACION CLIENTE | S1: Columna1
A2: 1099 | B2: 3015219527 | C2: 1.2144983e+08 | D2: M SIERRA FERRETEROS S.A.S. "MONTEVIDEO" | E2: 2.8937697e+09 | F2: 5.4981624e+08 | G2: 71436972 | H2: 0 | I2: 0 | J2: 71436972 | K2: 3.372149e+09 | L2: 90134981300 | M2: 901349813-9 | N2: BOGOTA - BOGOTA | O2: GRANDES CUENTAS | P2: GRANDES CUENTAS | Q2: MAYORISTA INDUSTRIAL | R2: =E2/$E$1757 -> 0.050767493 | S2: =Tabla3[[#This Row],[Subtotal]]/12 -> 2.4114747e+08
A3: 275 | B3: 1843490842 | C3: 2339354.4 | D3: CENTRO PINTUCOLOR S.A.S. | E3: 1.8411515e+09 | F3: 3.4981878e+08 | G3: 45194876 | H3: 0 | I3: 0 | J3: 45194876 | K3: 2.1457754e+09 | L3: 90058246400 | M3: 900582464-5 | N3: BARRANCABERMEJA - SANTANDER | O3: EVELIO GARCIA - SANTANDER | P3: EVELIO GARCIA - SANTANDER | Q3: GRAN DISTRIBUIDOR | R3: =E3/$E$1757 -> 0.032300651 | S3: =Tabla3[[#This Row],[Subtotal]]/12 -> 1.5342929e+08
A4: 676 | B4: 1209088709 | C4: 0 | D4: FERRETERIA TUBOLAMINAS S A-CALI | E4: 1209088709 | F4: 2.2972685e+08 | G4: 29330074 | H4: 2884477.1 | I4: 0 | J4: 32214551 | K4: 1.406601e+09 | L4: 89032442001 | M4: 890324420-0 | N4: CALI - VALLE DEL CAUCA | O4: JORGE CASTRO - VALLE DE CAUCA | P4: JORGE CASTRO - VALLE DE CAUCA | Q4: GRAN DISTRIBUIDOR | R4: =E4/$E$1757 -> 0.021211917 | S4: =Tabla3[[#This Row],[Subtotal]]/12 -> 1.0075739e+08
A5: 554 | B5: 1090617249 | C5: 4447639.6 | D5: FEDUSE S.A.S | E5: 1.0861696e+09 | F5: 2.0637223e+08 | G5: 26672949 | H5: 0 | I5: 0 | J5: 26672949 | K5: 1.2658689e+09 | L5: 89130321200 | M5: 891303212-9 | N5: GUADALAJARA DE BUGA - VALLE DE | O5: JORGE CASTRO - VALLE DE CAUCA | P5: JORGE CASTRO - VALLE DE CAUCA | Q5: GRAN DISTRIBUIDOR | R5: =E5/$E$1757 -> 0.019055458 | S5: =Tabla3[[#This Row],[Subtotal]]/12 -> 90514134
A6: 1143 | B6: 1.0557465e+09 | C6: 2149094.9 | D6: MATERIALES SU CONSTRUCCION S.A. | E6: 1.0535974e+09 | F6: 2.0018351e+08 | G6: 25275756 | H6: 0 | I6: 0 | J6: 25275756 | K6: 1.2285052e+09 | L6: 80014765000 | M6: 800147650-1 | N6: MEDELLIN - ANTIOQUIA | O6: ANTIOQUIA | P6: ANTIOQUIA | Q6: MAYORISTA INDUSTRIAL | R6: =E6/$E$1757 -> 0.018484021 | S6: =Tabla3[[#This Row],[Subtotal]]/12 -> 87799784
A7: 945 | B7: 974667488 | C7: 5068830.2 | D7: INDURRUEDAS S A S "BMANGA" | E7: 9.6959866e+08 | F7: 1.8422374e+08 | G7: 23659010 | H7: 0 | I7: 0 | J7: 23659010 | K7: 1.1301634e+09 | L7: 89020795600 | M7: 890207956-5 | N7: BUCARAMANGA - SANTANDER | O7: EVELIO GARCIA - SANTANDER | P7: EVELIO GARCIA - SANTANDER | Q7: MAYORISTA INDUSTRIAL | R7: =E7/$E$1757 -> 0.01701037 | S7: =Tabla3[[#This Row],[Subtotal]]/12 -> 80799888
A8: 1120 | B8: 9.5826145e+08 | C8: 10098824 | D8: MARTILLO DISTRIBUIDOR MAYORISTA S.A.S. | E8: 9.4816263e+08 | F8: 1.801509e+08 | G8: 23606260 | H8: 0 | I8: 0 | J8: 23606260 | K8: 1.1047073e+09 | L8: 90144410400 | M8: 901444104-1 | N8: CALI - VALLE DEL CAUCA | O8: JORGE CASTRO - VALLE DE CAUCA | P8: JORGE CASTRO - VALLE DE CAUCA | Q8: MAYORISTA INDUSTRIAL | R8: =E8/$E$1757 -> 0.016634302 | S8: =Tabla3[[#This Row],[Subtotal]]/12 -> 79013553
A9: 929 | B9: 940692124 | C9: 0 | D9: HOLCIM COLOMBIA S.A | E9: 940692124 | F9: 1.787315e+08 | G9: 22942086 | H9: 26153978 | I9: 0 | J9: 49096065 | K9: 1.0703276e+09 | L9: 86000980800 | M9: 860009808-5 | N9: BOGOTA - BOGOTA | O9: GRANDES CUENTAS | P9: GRANDES CUENTAS | Q9: MAYORISTA INDUSTRIAL | R9: =E9/$E$1757 -> 0.016503242 | S9: =Tabla3[[#This Row],[Subtotal]]/12 -> 78391010
A10: 1098 | B10: 688456772 | C10: 26187382 | D10: M SIERRA FERRETEROS S.A.S "TIENDA BLER CENTRO" | E10: 6.6226939e+08 | F10: 1.2583118e+08 | G10: 16556735 | H10: 0 | I10: 0 | J10: 16556735 | K10: 7.7154384e+08 | L10: 90134981301 | M10: 901349813-9 | N10: BOGOTA - BOGOTA | O10: GRANDES CUENTAS | P10: GRANDES CUENTAS | Q10: MAYORISTA INDUSTRIAL | R10: =E10/$E$1757 -> 0.01161867 | S10: =Tabla3[[#This Row],[Subtotal]]/12 -> 55189116
A11: 1285 | B11: 604504509 | C11: 0 | D11: ORTIZ MURCIA AMPARO/FERROCED | E11: 604504509 | F11: 1.1485586e+08 | G11: 15082294 | H11: 0 | I11: 0 | J11: 15082294 | K11: 7.0427807e+08 | L11: 3617999600 | M11: 36179996-0 | N11: NEIVA - HUILA | O11: WILSON SEPULVEDA - HUILA - CAQUETA | P11: WILSON SEPULVEDA - HUILA - CAQUETA | Q11: GRAN DISTRIBUIDOR | R11: =E11/$E$1757 -> 0.010605259 | S11: =Tabla3[[#This Row],[Subtotal]]/12 -> 50375376
A12: 1599 | B12: 583451906 | C12: 9140364.8 | D12: SIDOC S.A.S. "YUMBO" | E12: 5.7431154e+08 | F12: 1.0911919e+08 | G12: 14066875 | H12: 13504130 | I12: 0 | J12: 27571004 | K12: 6.5585973e+08 | L12: 89033302300 | M12: 890333023-8 | N12: YUMBO - VALLE DEL CAUCA | O12: JORGE CASTRO - VALLE DE CAUCA | P12: JORGE CASTRO - VALLE DE CAUCA | Q12: GRAN DISTRIBUIDOR | R12: =E12/$E$1757 -> 0.010075562 | S12: =Tabla3[[#This Row],[Subtotal]]/12 -> 47859295
A13: 1601 | B13: 515763330 | C13: 8331660.5 | D13: SIDOC S.A.S." PEREIRA / DOSQUEBRADAS" | E13: 5.0743167e+08 | F13: 96412017 | G13: 12414922 | H13: 13120700 | I13: 0 | J13: 25535621 | K13: 5.7830807e+08 | L13: 89033302308 | M13: 890333023-8 | N13: DOS QUEBRADAS - RISARALDA | O13: JORGE CASTRO - EJE CAFETERO | P13: JORGE CASTRO - EJE CAFETERO | Q13: GRAN DISTRIBUIDOR | R13: =E13/$E$1757 -> 0.0089022404 | S13: =Tabla3[[#This Row],[Subtotal]]/12 -> 42285972
... A1269: 101 | B1269: 1917719 | C1269: 0 | D1269: ARENAS PEREZ MARTHA CECILIA/FERREDEPOSITO LA 74 | E1269: 1917719 | F1269: 364366.61 | G1269: 0 | H1269: 0 | I1269: 0 | J1269: 0 | K1269: 2282085.6 | L1269: 5179534300 | M1269: 51795343-8 | N1269: BOGOTA - BOGOTA | O1269: DIANA ARENAS - LOCALIDAD BARRIOS UNIDOS | P1269: DIANA ARENAS - LOCALIDAD BARRIOS UNIDOS | Q1269: DISTRIBUIDOR | R1269: =E1269/$E$1757 -> 3.364393e-05 | S1269: =Tabla3[[#This Row],[Subtotal]]/12 -> 159809.92
A1270: 1676 | B1270: 1917067 | C1270: 0 | D1270: TRANSPORTADORA MERCANTIL LTDA | E1270: 1917067 | F1270: 164138.91 | G1270: 0 | H1270: 0 | I1270: 0 | J1270: 0 | K1270: 2081205.9 | L1270: 83009959600 | M1270: 830099596-4 | O1270: TRANSPORTADORAS | P1270: TRANSPORTADORAS | Q1270: PVP | R1270: =E1270/$E$1757 -> 3.3632492e-05 | S1270: =Tabla3[[#This Row],[Subtotal]]/12 -> 159755.58
A1271: 242 | B1271: 1913652 | C1271: 0 | D1271: CASTRO GUTIERREZ NORBERTO/MAFERRO SERVICIOS DE ACERO NC | E1271: 1913652 | F1271: 363593.88 | G1271: 0 | H1271: 0 | I1271: 0 | J1271: 0 | K1271: 2277245.9 | L1271: 8044920000 | M1271: 80449200-6 | N1271: CHIA - CUNDINAMARCA | O1271: OMAR MONTAÑA - SABANA CENTRO | P1271: OMAR MONTAÑA - SABANA CENTRO | Q1271: DISTRIBUIDOR | R1271: =E1271/$E$1757 -> 3.357258e-05 | S1271: =Tabla3[[#This Row],[Subtotal]]/12 -> 159471
A1272: 1655 | B1272: 1913471 | C1272: 0 | D1272: TECNOHIERROS SAS | E1272: 1913471 | F1272: 361279.49 | G1272: 0 | H1272: 0 | I1272: 0 | J1272: 0 | K1272: 2274750.5 | L1272: 90143500200 | M1272: 901435002-0 | N1272: BOGOTA - BOGOTA | O1272: TUL SAS | P1272: TUL SAS | Q1272: DISTRIBUIDOR | R1272: =E1272/$E$1757 -> 3.3569404e-05 | S1272: =Tabla3[[#This Row],[Subtotal]]/12 -> 159455.92
A1273: 1754 | B1273: 1912969 | C1273: 0 | D1273: ZUÑIGA CARVAJAL ADRIANA DEL PILAR / OMEGA FERRETERIAS | E1273: 1912969 | F1273: 363464.11 | G1273: 0 | H1273: 0 | I1273: 0 | J1273: 0 | K1273: 2276433.1 | L1273: 101020400900 | M1273: 1010204009-1 | N1273: BOGOTA - BOGOTA | O1273: ALFONSO ALBA - LOCALIDAD ENGATIVA | P1273: ALFONSO ALBA - LOCALIDAD ENGATIVA | Q1273: DISTRIBUIDOR | R1273: =E1273/$E$1757 -> 3.3560597e-05 | S1273: =Tabla3[[#This Row],[Subtotal]]/12 -> 159414.08
A1274: 103 | B1274: 1908741 | C1274: 0 | D1274: ARFOS FERRETERIA LTDA | E1274: 1908741 | F1274: 362660.79 | G1274: 18627.75 | H1274: 0 | I1274: 0 | J1274: 18627.75 | K1274: 2252774 | L1274: 90021111200 | M1274: 900211112-7 | N1274: BOGOTA - BOGOTA | O1274: ALFONSO ALBA - LOCALIDAD ENGATIVA | P1274: ALFONSO ALBA - LOCALIDAD ENGATIVA | Q1274: DISTRIBUIDOR | R1274: =E1274/$E$1757 -> 3.3486423e-05 | S1274: =Tabla3[[#This Row],[Subtotal]]/12 -> 159061.75
A1275: 1714 | B1275: 1898492 | C1275: 0 | D1275: VASQUEZ MARIA ELISA/FERRETERIA J.I RODRIGUEZ | E1275: 1898492 | F1275: 360713.48 | G1275: 0 | H1275: 0 | I1275: 0 | J1275: 0 | K1275: 2259205.5 | L1275: 3977759000 | M1275: 39777590-0 | N1275: BOGOTA - BOGOTA | O1275: ALFONSO ALBA - LOCALIDAD SUBA | P1275: ALFONSO ALBA - LOCALIDAD SUBA | Q1275: DISTRIBUIDOR | R1275: =E1275/$E$1757 -> 3.3306617e-05 | S1275: =Tabla3[[#This Row],[Subtotal]]/12 -> 158207.67
A1276: 1055 | B1276: 1896550 | C1276: 0 | D1276: LAGUNA CAÑON HUGO JAVIER/TECNICOLOR | E1276: 1896550 | F1276: 360344.5 | G1276: 0 | H1276: 0 | I1276: 0 | J1276: 0 | K1276: 2256894.5 | L1276: 1731990400 | M1276: 17319904-6 | N1276: VILLAVICENCIO - META | O1276: WILSON SEPULVEDA - META | P1276: WILSON SEPULVEDA - META | Q1276: GRAN DISTRIBUIDOR | R1276: =E1276/$E$1757 -> 3.3272547e-05 | S1276: =Tabla3[[#This Row],[Subtotal]]/12 -> 158045.83
A1277: 1582 | B1277: 1891712 | C1277: 0 | D1277: SANTOS BARRERA MAURICIO ANIBAL/FERREDEPOSITO CONSTRUYA | E1277: 1891712 | F1277: 359425.28 | G1277: 0 | H1277: 0 | I1277: 0 | J1277: 0 | K1277: 2251137.3 | L1277: 568987100 | M1277: 5689871-4 | N1277: BOGOTA - BOGOTA | O1277: ALFONSO ALBA - LOCALIDAD USAQUEN | P1277: ALFONSO ALBA - LOCALIDAD USAQUEN | Q1277: DISTRIBUIDOR | R1277: =E1277/$E$1757 -> 3.3187671e-05 | S1277: =Tabla3[[#This Row],[Subtotal]]/12 -> 157642.67
A1278: 854 | B1278: 1868310 | C1278: 0 | D1278: GUERRERO SANCHEZ HECTOR EMANUEL / MULTICOLORES GS | E1278: 1868310 | F1278: 354978.9 | G1278: 0 | H1278: 0 | I1278: 0 | J1278: 0 | K1278: 2223288.9 | L1278: 100004843800 | M1278: 1000048438-0 | N1278: BOGOTA - BOGOTA | O1278: ALFONSO ALBA - LOCALIDAD USAQUEN | P1278: ALFONSO ALBA - LOCALIDAD USAQUEN | Q1278: DISTRIBUIDOR | R1278: =E1278/$E$1757 -> 3.2777112e-05 | S1278: =Tabla3[[#This Row],[Subtotal]]/12 -> 155692.5
A1279: 46 | B1279: 1859752 | C1279: 0 | D1279: AGUILAR VASQUEZ MARTHA LUCIA/FERRETEJAS Y MANGUERAS | E1279: 1859752 | F1279: 353352.88 | G1279: 0 | H1279: 0 | I1279: 0 | J1279: 0 | K1279: 2213104.9 | L1279: 3541059100 | M1279: 35410591-8 | N1279: ZIPAQUIRA - CUNDINAMARCA | O1279: OMAR MONTAÑA - SABANA CENTRO | P1279: OMAR MONTAÑA - SABANA CENTRO | Q1279: DISTRIBUIDOR | R1279: =E1279/$E$1757 -> 3.2626973e-05 | S1279: =Tabla3[[#This Row],[Subtotal]]/12 -> 154979.33
A1280: 1083 | B1280: 1856876 | C1280: 0 | D1280: LOPEZ RODRIGUEZ ADRIANA MARCELA | E1280: 1856876 | F1280: 352806.44 | G1280: 0 | H1280: 0 | I1280: 0 | J1280: 0 | K1280: 2209682.4 | L1280: 4362785300 | M1280: 43627853 | N1280: MOSQUERA - CUNDINAMARCA | O1280: EMPLEADO | P1280: EMPLEADO | Q1280: INDUSTRIAL 2 | R1280: =E1280/$E$1757 -> 3.2576517e-05 | S1280: =Tabla3[[#This Row],[Subtotal]]/12 -> 154739.67
A1281: 1114 | B1281: 1856802 | C1281: 0 | D1281: MARIO RODRIGUEZ GUTIERREZ | E1281: 1856802 | F1281: 352792.38 | G1281: 0 | H1281: 0 | I1281: 0 | J1281: 0 | K1281: 2209594.4 | L1281: 7923020500 | M1281: 79230205 | N1281: BOGOTA - BOGOTA | O1281: ALFONSO ALBA - LOCALIDAD SUBA | P1281: ALFONSO ALBA - LOCALIDAD SUBA | Q1281: DISTRIBUIDOR | R1281: =E1281/$E$1757 -> 3.2575219e-05 | S1281: =Tabla3[[#This Row],[Subtotal]]/12 -> 154733.5
A1282: 245 | B1282: 1850724 | C1282: 0 | D1282: CASTRO LOPEZ DIEGO JAVIER/ ESTRUCTURAS METALICAS DEL CAUCA | E1282: 1850724 | F1282: 351637.56 | G1282: 46268.1 | H1282: 0 | I1282: 0 | J1282: 46268.1 | K1282: 2156093.5 | L1282: 1054755800 | M1282: 10547558-2 | N1282: POPAYAN - CAUCA | O1282: JORGE CASTRO - CAUCA | P1282: JORGE CASTRO - CAUCA | Q1282: DISTRIBUIDOR | R1282: =E1282/$E$1757 -> 3.2468588e-05 | S1282: =Tabla3[[#This Row],[Subtotal]]/12 -> 154227
... A1565: 1122 | B1565: 427392 | C1565: 0 | D1565: MARTIN BARRETO CAMPO ELIAS/MULTICOLOR CAMPOS | E1565: 427392 | F1565: 81204.48 | G1565: 0 | H1565: 0 | I1565: 0 | J1565: 0 | K1565: 508596.48 | L1565: 7956394300 | M1565: 79563943-3 | N1565: SOACHA - CUNDINAMARCA | O1565: ALEJANDRO CARANTON -SOACHA - SIBATE | P1565: ALEJANDRO CARANTON -SOACHA - SIBATE | Q1565: DISTRIBUIDOR | R1565: =E1565/$E$1757 -> 7.4980467e-06 | S1565: =Tabla3[[#This Row],[Subtotal]]/12 -> 35616
A1566: 1305 | B1566: 420412 | C1566: 0 | D1566: PAEZ QUITO FABIO GUILLERMO | E1566: 420412 | F1566: 79878.28 | G1566: 0 | H1566: 0 | I1566: 0 | J1566: 0 | K1566: 500290.28 | L1566: 8017211900 | M1566: 80172119 | O1566: EMPLEADO | P1566: EMPLEADO | Q1566: INDUSTRIAL 2 | R1566: =E1566/$E$1757 -> 7.3755915e-06 | S1566: =Tabla3[[#This Row],[Subtotal]]/12 -> 35034.333
A1567: 1180 | B1567: 416737 | C1567: 0 | D1567: MONTAÑEZ SILVA EDISON YAMID / FERRELECTRICOS MONTAÑEZ | E1567: 416737 | F1567: 79180.03 | G1567: 0 | H1567: 0 | I1567: 0 | J1567: 0 | K1567: 495917.03 | L1567: 101902499800 | M1567: 1019024998-9 | N1567: BOGOTA - BOGOTA | O1567: TUL SAS | P1567: TUL SAS | Q1567: DISTRIBUIDOR | R1567: =E1567/$E$1757 -> 7.3111183e-06 | S1567: =Tabla3[[#This Row],[Subtotal]]/12 -> 34728.083
A1568: 63 | B1568: 415986 | C1568: 0 | D1568: ALEMAN VILLAMIZAR DIEGO ANDRES | E1568: 415986 | F1568: 79037.34 | G1568: 0 | H1568: 0 | I1568: 0 | J1568: 0 | K1568: 495023.34 | L1568: 103164554300 | M1568: 1031645543 | N1568: BOGOTA - BOGOTA | O1568: EMPLEADO | P1568: EMPLEADO | Q1568: INDUSTRIAL 2 | R1568: =E1568/$E$1757 -> 7.297943e-06 | S1568: =Tabla3[[#This Row],[Subtotal]]/12 -> 34665.5
A1569: 1749 | B1569: 411537 | C1569: 0 | D1569: ZUBIETA VEGA OSWALDO / FERRESUMINISTRO E INSUMOS DE LA SABANA | E1569: 411537 | F1569: 78192.03 | G1569: 0 | H1569: 0 | I1569: 0 | J1569: 0 | K1569: 489729.03 | L1569: 1134945900 | M1569: 11349459-6 | N1569: ZIPAQUIRA - CUNDINAMARCA | O1569: OMAR MONTAÑA - SABANA CENTRO | P1569: OMAR MONTAÑA - SABANA CENTRO | Q1569: DISTRIBUIDOR | R1569: =E1569/$E$1757 -> 7.219891e-06 | S1569: =Tabla3[[#This Row],[Subtotal]]/12 -> 34294.75
A1570: 1151 | B1570: 411460 | C1570: 0 | D1570: MEJIA SUAREZ CLARA INES | E1570: 411460 | F1570: 78177.4 | G1570: 0 | H1570: 0 | I1570: 0 | J1570: 0 | K1570: 489637.4 | L1570: 5196653600 | M1570: 51966536 | N1570: BOGOTA - BOGOTA | O1570: EMPLEADO | P1570: EMPLEADO | Q1570: INDUSTRIAL 2 | R1570: =E1570/$E$1757 -> 7.2185401e-06 | S1570: =Tabla3[[#This Row],[Subtotal]]/12 -> 34288.333
A1571: 1695 | B1571: 411201 | C1571: 0 | D1571: URBANCAR SAS | E1571: 411201 | F1571: 78128.19 | G1571: 0 | H1571: 0 | I1571: 0 | J1571: 0 | K1571: 489329.19 | L1571: 90088400000 | M1571: 900884000-8 | N1571: MADRID - CUNDINAMARCA | O1571: DIANA ARENAS - SABANA OCCIDENTE | P1571: DIANA ARENAS - SABANA OCCIDENTE | Q1571: DISTRIBUIDOR | R1571: =E1571/$E$1757 -> 7.2139963e-06 | S1571: =Tabla3[[#This Row],[Subtotal]]/12 -> 34266.75
A1572: 1513 | B1572: 404324 | C1572: 0 | D1572: RODRIGUEZ VASQUEZ OMAR ARMANDO/FERRELECTRICOS RG | E1572: 404324 | F1572: 76821.56 | G1572: 0 | H1572: 0 | I1572: 0 | J1572: 0 | K1572: 481145.56 | L1572: 1943226900 | M1572: 19432269-7 | N1572: EL COLEGIO - CUNDINAMARCA | O1572: OMAR MONTAÑA -SUR TOLIMA | P1572: OMAR MONTAÑA -SUR TOLIMA | Q1572: DISTRIBUIDOR | R1572: =E1572/$E$1757 -> 7.0933481e-06 | S1572: =Tabla3[[#This Row],[Subtotal]]/12 -> 33693.667
A1573: 1135 | B1573: 389754 | C1573: 0 | D1573: MATALLANA CUERVO FLOR ALBA/DEPOSITO DE MATERIALES EL CEDRO | E1573: 389754 | F1573: 74053.26 | G1573: 0 | H1573: 0 | I1573: 0 | J1573: 0 | K1573: 463807.26 | L1573: 3980886200 | M1573: 39808862-3 | N1573: TABIO - CUNDINAMARCA | O1573: OMAR MONTAÑA - SABANA CENTRO | P1573: OMAR MONTAÑA - SABANA CENTRO | Q1573: DISTRIBUIDOR | R1573: =E1573/$E$1757 -> 6.8377361e-06 | S1573: =Tabla3[[#This Row],[Subtotal]]/12 -> 32479.5
A1574: 1068 | B1574: 387504 | C1574: 0 | D1574: LEON CASTAÑEDA CARLOS ANDRES / FERRELECTRICOS C Y C 2 | E1574: 387504 | F1574: 73625.76 | G1574: 0 | H1574: 0 | I1574: 0 | J1574: 0 | K1574: 461129.76 | L1574: 101429982200 | M1574: 1014299822-3 | N1574: BOGOTA - BOGOTA | O1574: ALFONSO ALBA - LOCALIDAD ENGATIVA | P1574: ALFONSO ALBA - LOCALIDAD ENGATIVA | Q1574: DISTRIBUIDOR | R1574: =E1574/$E$1757 -> 6.7982627e-06 | S1574: =Tabla3[[#This Row],[Subtotal]]/12 -> 32292
A1575: 1132 | B1575: 381447 | C1575: 0 | D1575: MARTINEZ PRIETO MARTHA DIVIA / PAPELERIA Y CAFÉ INTERNET LA UNIVERSAL | E1575: 381447 | F1575: 72474.93 | G1575: 0 | H1575: 0 | I1575: 0 | J1575: 0 | K1575: 453921.93 | L1575: 2063433100 | M1575: 20634331-7 | N1575: GUADUAS - CUNDINAMARCA | O1575: OMAR MONTAÑA - NTE DEL TOLIMA | P1575: OMAR MONTAÑA - NTE DEL TOLIMA | Q1575: DISTRIBUIDOR | R1575: =E1575/$E$1757 -> 6.6920004e-06 | S1575: =Tabla3[[#This Row],[Subtotal]]/12 -> 31787.25
A1576: 47 | B1576: 380252.1 | C1576: 0 | D1576: AIDA JANETH GAMEZ VILLARRAGA | E1576: 380252.1 | F1576: 72247.9 | G1576: 0 | H1576: 0 | I1576: 0 | J1576: 0 | K1576: 452500 | L1576: 5156827300 | M1576: 51568273 | N1576: BOGOTA - BOGOTA | O1576: E - COMMERCE | P1576: E - COMMERCE | Q1576: PVP | R1576: =E1576/$E$1757 -> 6.6710374e-06 | S1576: =Tabla3[[#This Row],[Subtotal]]/12 -> 31687.675
A1577: 1200 | B1577: 375110 | C1577: 0 | D1577: MORENO JIMENEZ JOSE SEIR/FERRETERIA EL AMIGASO | E1577: 375110 | F1577: 71270.9 | G1577: 0 | H1577: 0 | I1577: 0 | J1577: 0 | K1577: 446380.9 | L1577: 7983989200 | M1577: 79839892-2 | N1577: BOGOTA - BOGOTA | O1577: ALEJANDRO CARANTON -LOCALIDAD KENNEDY | P1577: ALEJANDRO CARANTON -LOCALIDAD KENNEDY | Q1577: DISTRIBUIDOR | R1577: =E1577/$E$1757 -> 6.5808258e-06 | S1577: =Tabla3[[#This Row],[Subtotal]]/12 -> 31259.167
A1578: 1447 | B1578: 371780 | C1578: 0 | D1578: RAMIREZ ZABALA MANUEL/ALMACEN Y FERRETERIA EL PROVEEDOR DEL CONSTRUCTOR | E1578: 371780 | F1578: 70638.2 | G1578: 0 | H1578: 0 | I1578: 0 | J1578: 0 | K1578: 442418.2 | L1578: 1923875000 | M1578: 19238750-8 | N1578: BOGOTA - BOGOTA | O1578: DIANA ARENAS - LOCALIDAD CHAPINERO | P1578: DIANA ARENAS - LOCALIDAD CHAPINERO | Q1578: DISTRIBUIDOR | R1578: =E1578/$E$1757 -> 6.5224052e-06 | S1578: =Tabla3[[#This Row],[Subtotal]]/12 -> 30981.667
... A1581: 577 | B1581: 357850 | C1581: 0 | D1581: FERREDEPOSITO JN HNOS S.A.S. | E1581: 357850 | F1581: 67991.5 | G1581: 0 | H1581: 0 | I1581: 0 | J1581: 0 | K1581: 425841.5 | L1581: 90145839800 | M1581: 901458398-0 | N1581: BOGOTA - BOGOTA | O1581: DIANA ARENAS - LOCALIDAD BARRIOS UNIDOS | P1581: DIANA ARENAS - LOCALIDAD BARRIOS UNIDOS | Q1581: DISTRIBUIDOR | R1581: =E1581/$E$1757 -> 6.2780211e-06 | S1581: =Tabla3[[#This Row],[Subtotal]]/12 -> 29820.833
A1582: 527 | B1582: 357847.6 | C1582: 0 | D1582: ENLACES E INGENIERIA SAS | E1582: 357847.6 | F1582: 67991.04 | G1582: 0 | H1582: 0 | I1582: 0 | J1582: 0 | K1582: 425838.64 | L1582: 90132961300 | M1582: 901329613-7 | O1582: MOSTRADOR | P1582: MOSTRADOR | Q1582: PVP | R1582: =E1582/$E$1757 -> 6.277979e-06 | S1582: =Tabla3[[#This Row],[Subtotal]]/12 -> 29820.633
A1583: 507 | B1583: 357204 | C1583: 0 | D1583: EDWIN HERNAN AMORTEGUI RODRIGUEZ | E1583: 357204 | F1583: 67868.76 | G1583: 0 | H1583: 0 | I1583: 0 | J1583: 0 | K1583: 425072.76 | L1583: 8007527300 | M1583: 80075273-7 | N1583: BOGOTA - BOGOTA | O1583: TUL SAS | P1583: TUL SAS | Q1583: DISTRIBUIDOR | R1583: =E1583/$E$1757 -> 6.2666879e-06 | S1583: =Tabla3[[#This Row],[Subtotal]]/12 -> 29767
A1584: 1196 | B1584: 352746 | C1584: 0 | D1584: MORENO BAQUERO LUIS ALBERTO/MULTI - TONOS MORENO | E1584: 352746 | F1584: 67021.74 | G1584: 0 | H1584: 0 | I1584: 0 | J1584: 0 | K1584: 419767.74 | L1584: 107836913500 | M1584: 1078369135-5 | N1584: TABIO - CUNDINAMARCA | O1584: OMAR MONTAÑA - SABANA CENTRO | P1584: OMAR MONTAÑA - SABANA CENTRO | Q1584: DISTRIBUIDOR | R1584: =E1584/$E$1757 -> 6.188478e-06 | S1584: =Tabla3[[#This Row],[Subtotal]]/12 -> 29395.5
A1585: 1268 | B1585: 352746 | C1585: 0 | D1585: OJEDA ROJAS WILLIAM DAVID/ALMACEN EL PUNTO DEL COLOR WD | E1585: 352746 | F1585: 67021.74 | G1585: 0 | H1585: 0 | I1585: 0 | J1585: 0 | K1585: 419767.74 | L1585: 102301683701 | M1585: 1023016837-2 | N1585: BOGOTA - BOGOTA | O1585: NORMA AGUILAR - LOCALIDAD CIUDAD BOLIVAR | P1585: NORMA AGUILAR - LOCALIDAD CIUDAD BOLIVAR | Q1585: DISTRIBUIDOR | R1585: =E1585/$E$1757 -> 6.188478e-06 | S1585: =Tabla3[[#This Row],[Subtotal]]/12 -> 29395.5
A1586: 667 | B1586: 351772 | C1586: 0 | D1586: FERRETERIA SUMINISTROS INDUSTRIALES S.A.S. | E1586: 351772 | F1586: 66836.68 | G1586: 0 | H1586: 0 | I1586: 0 | J1586: 0 | K1586: 418608.68 | L1586: 80500373900 | M1586: 805003739-8 | N1586: CALI - VALLE DEL CAUCA | O1586: JORGE CASTRO - VALLE DE CAUCA | P1586: JORGE CASTRO - VALLE DE CAUCA | Q1586: DISTRIBUIDOR | R1586: =E1586/$E$1757 -> 6.1713904e-06 | S1586: =Tabla3[[#This Row],[Subtotal]]/12 -> 29314.333
A1587: 1235 | B1587: 351240 | C1587: 0 | D1587: MUÑOZ POSSO RODRIGO / CASA DEL PINTOR | E1587: 351240 | F1587: 66735.6 | G1587: 0 | H1587: 0 | I1587: 0 | J1587: 0 | K1587: 417975.6 | L1587: 1010013100 | M1587: 10100131-2 | N1587: PEREIRA | O1587: JORGE CASTRO - EJE CAFETERO | P1587: JORGE CASTRO - EJE CAFETERO | Q1587: DISTRIBUIDOR | R1587: =E1587/$E$1757 -> 6.1620571e-06 | S1587: =Tabla3[[#This Row],[Subtotal]]/12 -> 29270
A1588: 1434 | B1588: 350802 | C1588: 0 | D1588: RAFAEL RUGE | E1588: 350802 | F1588: 66652.38 | G1588: 0 | H1588: 0 | I1588: 0 | J1588: 0 | K1588: 417454.38 | L1588: 8026551700 | M1588: 80265517-4 | N1588: BOGOTA - BOGOTA | O1588: TUL SAS | P1588: TUL SAS | Q1588: DISTRIBUIDOR | R1588: =E1588/$E$1757 -> 6.154373e-06 | S1588: =Tabla3[[#This Row],[Subtotal]]/12 -> 29233.5
A1589: 351 | B1589: 348430 | C1589: 0 | D1589: CONSTRUYENDO FACIL S.A.S. | E1589: 348430 | F1589: 66201.7 | G1589: 0 | H1589: 0 | I1589: 0 | J1589: 0 | K1589: 414631.7 | L1589: 90189752100 | M1589: 901897521-3 | N1589: SANTANA - BOYACA | O1589: MARTIN BALLESTEROS - SANTANDER / NTE SANTANDER | P1589: MARTIN BALLESTEROS - SANTANDER / NTE SANTANDER | Q1589: DISTRIBUIDOR | R1589: =E1589/$E$1757 -> 6.1127593e-06 | S1589: =Tabla3[[#This Row],[Subtotal]]/12 -> 29035.833
A1590: 60 | B1590: 347560 | C1590: 0 | D1590: ALDANA JOSE GREGORIO/LA FERIA DE LAS PINTURAS | E1590: 347560 | F1590: 66036.4 | G1590: 0 | H1590: 0 | I1590: 0 | J1590: 0 | K1590: 413596.4 | L1590: 1705790200 | M1590: 17057902-6 | N1590: BOGOTA - BOGOTA | O1590: NORMA AGUILAR - LOCALIDAD MARTIRES | P1590: NORMA AGUILAR - LOCALIDAD MARTIRES | Q1590: DISTRIBUIDOR | R1590: =E1590/$E$1757 -> 6.0974962e-06 | S1590: =Tabla3[[#This Row],[Subtotal]]/12 -> 28963.333
A1591: 196 | B1591: 341724 | C1591: 0 | D1591: CARDENAS CHAVARRO RICARDO | E1591: 341724 | F1591: 64927.56 | G1591: 0 | H1591: 0 | I1591: 0 | J1591: 0 | K1591: 406651.56 | L1591: 101900685600 | M1591: 1019006856-5 | N1591: BOGOTA - BOGOTA | O1591: TUL SAS | P1591: TUL SAS | Q1591: DISTRIBUIDOR | R1591: =E1591/$E$1757 -> 5.9951111e-06 | S1591: =Tabla3[[#This Row],[Subtotal]]/12 -> 28477
A1592: 437 | B1592: 340585 | C1592: 0 | D1592: DIAZ BLANCA/TIENDA PAPELERA | E1592: 340585 | F1592: 64711.15 | G1592: 0 | H1592: 0 | I1592: 0 | J1592: 0 | K1592: 405296.15 | L1592: 4146579200 | M1592: 41465792-1 | N1592: BOGOTA - BOGOTA | O1592: NORMA AGUILAR - LOCALIDAD SANTA FE | P1592: NORMA AGUILAR - LOCALIDAD SANTA FE | Q1592: DISTRIBUIDOR | R1592: =E1592/$E$1757 -> 5.9751288e-06 | S1592: =Tabla3[[#This Row],[Subtotal]]/12 -> 28382.083
A1593: 1665 | B1593: 339519 | C1593: 0 | D1593: TORO MANJARES DEYANIRA/PINTU FACA | E1593: 339519 | F1593: 64508.61 | G1593: 0 | H1593: 0 | I1593: 0 | J1593: 0 | K1593: 404027.61 | L1593: 3553154000 | M1593: 35531540-1 | N1593: FACATATIVA - CUNDINAMARCA | O1593: DIANA ARENAS - SABANA OCCIDENTE | P1593: DIANA ARENAS - SABANA OCCIDENTE | Q1593: DISTRIBUIDOR | R1593: =E1593/$E$1757 -> 5.9564272e-06 | S1593: =Tabla3[[#This Row],[Subtotal]]/12 -> 28293.25
A1594: 1502 | B1594: 338248 | C1594: 0 | D1594: RODRIGUEZ HERNANDEZ SONIA JALENNY | E1594: 338248 | F1594: 64267.12 | G1594: 0 | H1594: 0 | I1594: 0 | J1594: 0 | K1594: 402515.12 | L1594: 102301770400 | M1594: 1023017704-6 | N1594: BOGOTA - BOGOTA | O1594: NORMA AGUILAR - LOCALIDAD USME | P1594: NORMA AGUILAR - LOCALIDAD USME | Q1594: DISTRIBUIDOR | R1594: =E1594/$E$1757 -> 5.9341291e-06 | S1594: =Tabla3[[#This Row],[Subtotal]]/12 -> 28187.333
... A1637: 1402 | B1637: 201806 | C1637: 0 | D1637: PORTON VERDE PROPIEDAD HORIZONTAL | E1637: 201806 | F1637: 36443.14 | G1637: 0 | H1637: 0 | I1637: 0 | J1637: 0 | K1637: 238249.14 | L1637: 90066168400 | M1637: 900661684-8 | N1637: BOGOTA - BOGOTA | O1637: E - COMMERCE | P1637: E - COMMERCE | Q1637: PVP | R1637: =E1637/$E$1757 -> 3.5404285e-06 | S1637: =Tabla3[[#This Row],[Subtotal]]/12 -> 16817.167
A1638: 1008 | B1638: 200868 | C1638: 0 | D1638: JOSE ALONSO BEJARANO URREGO | E1638: 200868 | F1638: 35884.92 | G1638: 0 | H1638: 0 | I1638: 0 | J1638: 0 | K1638: 236752.92 | L1638: 8041258200 | M1638: 80412582-4 | O1638: TUL SAS | P1638: TUL SAS | Q1638: DISTRIBUIDOR | R1638: =E1638/$E$1757 -> 3.5239725e-06 | S1638: =Tabla3[[#This Row],[Subtotal]]/12 -> 16739
A1639: 328 | B1639: 200632.54 | C1639: 0 | D1639: COMPAÑIA DE SERVICIOS ELECTRICOS INTEGRALES SAS | E1639: 200632.54 | F1639: 38120.18 | G1639: 0 | H1639: 0 | I1639: 0 | J1639: 0 | K1639: 238752.72 | L1639: 90033948800 | M1639: 900339488-1 | N1639: COTA - CUNDINAMARCA | O1639: MOSTRADOR | P1639: MOSTRADOR | Q1639: PVP | R1639: =E1639/$E$1757 -> 3.5198416e-06 | S1639: =Tabla3[[#This Row],[Subtotal]]/12 -> 16719.378
A1640: 1112 | B1640: 196639 | C1640: 0 | D1640: MARIE FRANCE DUPRE RINCON | E1640: 196639 | F1640: 36411.41 | G1640: 0 | H1640: 0 | I1640: 0 | J1640: 0 | K1640: 233050.41 | L1640: 5156195500 | M1640: 51561955-0 | N1640: BOGOTA - BOGOTA | O1640: E - COMMERCE | P1640: E - COMMERCE | Q1640: PVP | R1640: =E1640/$E$1757 -> 3.4497801e-06 | S1640: =Tabla3[[#This Row],[Subtotal]]/12 -> 16386.583
A1641: 1126 | B1641: 195210.92 | C1641: 0 | D1641: MARTINEZ DIEGO | E1641: 195210.92 | F1641: 37090.07 | G1641: 0 | H1641: 0 | I1641: 0 | J1641: 0 | K1641: 232300.99 | L1641: 9153637600 | M1641: 91536376 | N1641: COTA - CUNDINAMARCA | O1641: E - COMMERCE | P1641: E - COMMERCE | Q1641: PVP | R1641: =E1641/$E$1757 -> 3.4247262e-06 | S1641: =Tabla3[[#This Row],[Subtotal]]/12 -> 16267.577
A1642: 1712 | B1642: 192048 | C1642: 0 | D1642: VARGAS SANTOS PABLO ENRIQUE / DEPOSITO FERRETERIA LOS VARGAS | E1642: 192048 | F1642: 36489.12 | G1642: 0 | H1642: 0 | I1642: 0 | J1642: 0 | K1642: 228537.12 | L1642: 296096300 | M1642: 2960963-3 | N1642: FUNZA - CUNDINAMARCA | O1642: DIANA ARENAS - SABANA OCCIDENTE | P1642: DIANA ARENAS - SABANA OCCIDENTE | Q1642: DISTRIBUIDOR | R1642: =E1642/$E$1757 -> 3.3692368e-06 | S1642: =Tabla3[[#This Row],[Subtotal]]/12 -> 16004
A1643: 1626 | B1643: 190602 | C1643: 0 | D1643: SONIA RUEDA SANTANDER | E1643: 190602 | F1643: 33934.38 | G1643: 0 | H1643: 0 | I1643: 0 | J1643: 0 | K1643: 224536.38 | L1643: 5214564400 | M1643: 52145644-5 | N1643: BOGOTA - BOGOTA | O1643: TUL SAS | P1643: TUL SAS | Q1643: DISTRIBUIDOR | R1643: =E1643/$E$1757 -> 3.3438686e-06 | S1643: =Tabla3[[#This Row],[Subtotal]]/12 -> 15883.5
A1644: 1433 | B1644: 189243.7 | C1644: 0 | D1644: RAFAEL ALEJANDRO CABIATIVA | E1644: 189243.7 | F1644: 35956.3 | G1644: 0 | H1644: 0 | I1644: 0 | J1644: 0 | K1644: 225200 | L1644: 8075820200 | M1644: 80758202 | N1644: BOGOTA - BOGOTA | O1644: E - COMMERCE | P1644: E - COMMERCE | Q1644: PVP | R1644: =E1644/$E$1757 -> 3.320039e-06 | S1644: =Tabla3[[#This Row],[Subtotal]]/12 -> 15770.308
A1645: 158 | B1645: 186638.72 | C1645: 0 | D1645: BRAULIO MARQUEZ | E1645: 186638.72 | F1645: 35461.36 | G1645: 0 | H1645: 0 | I1645: 0 | J1645: 0 | K1645: 222100.08 | L1645: 1939750600 | M1645: 19397506 | N1645: CAJICA - CUNDINAMARCA | O1645: E - COMMERCE | P1645: E - COMMERCE | Q1645: PVP | R1645: =E1645/$E$1757 -> 3.2743379e-06 | S1645: =Tabla3[[#This Row],[Subtotal]]/12 -> 15553.227
A1646: 1314 | B1646: 182094 | C1646: 0 | D1646: PANIAGUA JARA ANGELA | E1646: 182094 | F1646: 34597.86 | G1646: 0 | H1646: 0 | I1646: 0 | J1646: 0 | K1646: 216691.86 | L1646: 101905389200 | M1646: 1019053892 | N1646: BOGOTA - BOGOTA | O1646: EMPLEADO | P1646: EMPLEADO | Q1646: INDUSTRIAL 2 | R1646: =E1646/$E$1757 -> 3.1946066e-06 | S1646: =Tabla3[[#This Row],[Subtotal]]/12 -> 15174.5
A1647: 1204 | B1647: 181169 | C1647: 0 | D1647: MORENO SEGUNDO | E1647: 181169 | F1647: 34422.11 | G1647: 0 | H1647: 0 | I1647: 0 | J1647: 0 | K1647: 215591.11 | L1647: 421694400 | M1647: 4216944 | N1647: BOGOTA - BOGOTA | O1647: EMPLEADO | P1647: EMPLEADO | Q1647: INDUSTRIAL 2 | R1647: =E1647/$E$1757 -> 3.1783787e-06 | S1647: =Tabla3[[#This Row],[Subtotal]]/12 -> 15097.417
A1648: 236 | B1648: 179460 | C1648: 0 | D1648: CASTILLO PRIETO MARCO ANTONIO/FERRELECTRICOS Y TORNILLOS L Y M | E1648: 179460 | F1648: 34097.4 | G1648: 0 | H1648: 0 | I1648: 0 | J1648: 0 | K1648: 213557.4 | L1648: 8039030800 | M1648: 80390308-6 | N1648: BOGOTA - BOGOTA | O1648: DIANA ARENAS - LOCALIDAD TEUSAQUILLO | P1648: DIANA ARENAS - LOCALIDAD TEUSAQUILLO | Q1648: DISTRIBUIDOR | R1648: =E1648/$E$1757 -> 3.1483965e-06 | S1648: =Tabla3[[#This Row],[Subtotal]]/12 -> 14955
A1649: 888 | B1649: 179435.36 | C1649: 0 | D1649: HERRAMIENTAS UNIDAS S.A.S | E1649: 179435.36 | F1649: 33142.72 | G1649: 0 | H1649: 0 | I1649: 0 | J1649: 0 | K1649: 212578.08 | L1649: 86006503600 | M1649: 860065036-4 | N1649: BOGOTA - BOGOTA | O1649: E - COMMERCE | P1649: E - COMMERCE | Q1649: PVP | R1649: =E1649/$E$1757 -> 3.1479642e-06 | S1649: =Tabla3[[#This Row],[Subtotal]]/12 -> 14952.947
A1650: 983 | B1650: 174537.82 | C1650: 0 | D1650: ISABEL PEÑA | E1650: 174537.82 | F1650: 33162.19 | G1650: 0 | H1650: 0 | I1650: 0 | J1650: 0 | K1650: 207700.01 | L1650: 4165467400 | M1650: 41654674 | N1650: BOGOTA - BOGOTA | O1650: E - COMMERCE | P1650: E - COMMERCE | Q1650: PVP | R1650: =E1650/$E$1757 -> 3.0620431e-06 | S1650: =Tabla3[[#This Row],[Subtotal]]/12 -> 14544.818
A1651: 282 | B1651: 170671.8 | C1651: 0 | D1651: CESAR AUGUSTO DIAZ CARRILLO | E1651: 170671.8 | F1651: 31477.64 | G1651: 0 | H1651: 0 | I1651: 0 | J1651: 0 | K1651: 202149.44 | L1651: 7914722000 | M1651: 79147220-3 | N1651: BOGOTA - BOGOTA | O1651: E - COMMERCE | P1651: E - COMMERCE | Q1651: PVP | R1651: =E1651/$E$1757 -> 2.9942187e-06 | S1651: =Tabla3[[#This Row],[Subtotal]]/12 -> 14222.65
A1652: 243 | B1652: 169072 | C1652: 0 | D1652: CASTRO JORGE MARIA | E1652: 169072 | F1652: 32123.68 | G1652: 0 | H1652: 0 | I1652: 0 | J1652: 0 | K1652: 201195.68 | L1652: 8050568200 | M1652: 80505682 | O1652: EMPLEADO | P1652: EMPLEADO | Q1652: INDUSTRIAL 2 | R1652: =E1652/$E$1757 -> 2.9661523e-06 | S1652: =Tabla3[[#This Row],[Subtotal]]/12 -> 14089.333
A1653: 299 | B1653: 169072 | C1653: 0 | D1653: COCA RAMIREZ KAREN VIVIANA | E1653: 169072 | F1653: 32123.68 | G1653: 0 | H1653: 0 | I1653: 0 | J1653: 0 | K1653: 201195.68 | L1653: 100781995500 | M1653: 1007819955 | N1653: MOSQUERA - CUNDINAMARCA | O1653: EMPLEADO | P1653: EMPLEADO | Q1653: INDUSTRIAL 2 | R1653: =E1653/$E$1757 -> 2.9661523e-06 | S1653: =Tabla3[[#This Row],[Subtotal]]/12 -> 14089.333
A1654: 57 | B1654: 168235.3 | C1654: 0 | D1654: ALBA STELLA CEPEDA DELGADO | E1654: 168235.3 | F1654: 31014.71 | G1654: 0 | H1654: 0 | I1654: 0 | J1654: 0 | K1654: 199250.01 | L1654: 4152383900 | M1654: 41523839 | N1654: BOGOTA - BOGOTA | O1654: E - COMMERCE | P1654: E - COMMERCE | Q1654: PVP | R1654: =E1654/$E$1757 -> 2.9514734e-06 | S1654: =Tabla3[[#This Row],[Subtotal]]/12 -> 14019.608
A1655: 932 | B1655: 166889.8 | C1655: 0 | D1655: HOLMAN ANDRES ABRIL UMBARILA | E1655: 166889.8 | F1655: 30759.06 | G1655: 0 | H1655: 0 | I1655: 0 | J1655: 0 | K1655: 197648.86 | L1655: 102081249800 | M1655: 1020812498-2 | N1655: BOGOTA - BOGOTA | O1655: E - COMMERCE | P1655: E - COMMERCE | Q1655: PVP | R1655: =E1655/$E$1757 -> 2.9278684e-06 | S1655: =Tabla3[[#This Row],[Subtotal]]/12 -> 13907.483
A1656: 1742 | B1656: 164705.9 | C1656: 0 | D1656: YINETH ACOSTA GUTIERREZ | E1656: 164705.9 | F1656: 31294.12 | G1656: 0 | H1656: 0 | I1656: 0 | J1656: 0 | K1656: 196000.02 | L1656: 5290657200 | M1656: 52906572-1 | N1656: BOGOTA - BOGOTA | O1656: E - COMMERCE | P1656: E - COMMERCE | Q1656: PVP | R1656: =E1656/$E$1757 -> 2.8895546e-06 | S1656: =Tabla3[[#This Row],[Subtotal]]/12 -> 13725.492
A1657: 546 | B1657: 164705.89 | C1657: 0 | D1657: FABIAN DAVID GARCIA CASTRO | E1657: 164705.89 | F1657: 31294.12 | G1657: 0 | H1657: 0 | I1657: 0 | J1657: 0 | K1657: 196000.01 | L1657: 7437929300 | M1657: 74379293 | N1657: SOACHA - CUNDINAMARCA | O1657: E - COMMERCE | P1657: E - COMMERCE | Q1657: PVP | R1657: =E1657/$E$1757 -> 2.8895544e-06 | S1657: =Tabla3[[#This Row],[Subtotal]]/12 -> 13725.491
A1658: 506 | B1658: 161341.32 | C1658: 0 | D1658: EDIFICIO EL ESCORIAL PROPIEDAD HORIZONTAL | E1658: 161341.32 | F1658: 30654.85 | G1658: 0 | H1658: 0 | I1658: 0 | J1658: 0 | K1658: 191996.17 | L1658: 83010480500 | M1658: 830104805-0 | N1658: BOGOTA - BOGOTA | O1658: E - COMMERCE | P1658: E - COMMERCE | Q1658: PVP | R1658: =E1658/$E$1757 -> 2.8305274e-06 | S1658: =Tabla3[[#This Row],[Subtotal]]/12 -> 13445.11
A1659: 1493 | B1659: 160506 | C1659: 0 | D1659: RODRIGUEZ CHAUX ADRIANA/ FERREPINTURAS CHAUX | E1659: 160506 | F1659: 30496.14 | G1659: 0 | H1659: 0 | I1659: 0 | J1659: 0 | K1659: 191002.14 | L1659: 39652839 | M1659: 39652839-1 | N1659: BOGOTA - BOGOTA | O1659: ALFONSO ALBA - LOCALIDAD SUBA | P1659: ALFONSO ALBA - LOCALIDAD SUBA | Q1659: DISTRIBUIDOR | R1659: =E1659/$E$1757 -> 2.8158727e-06 | S1659: =Tabla3[[#This Row],[Subtotal]]/12 -> 13375.5
A1660: 350 | B1660: 158257 | C1660: 0 | D1660: CONSTRUYAME S.A.S. | E1660: 158257 | F1660: 30068.83 | G1660: 0 | H1660: 0 | I1660: 0 | J1660: 0 | K1660: 188325.83 | L1660: 90037060000 | M1660: 900370600-0 | N1660: BOGOTA - BOGOTA | O1660: ALFONSO ALBA - LOCALIDAD ENGATIVA | P1660: ALFONSO ALBA - LOCALIDAD ENGATIVA | Q1660: DISTRIBUIDOR | R1660: =E1660/$E$1757 -> 2.7764169e-06 | S1660: =Tabla3[[#This Row],[Subtotal]]/12 -> 13188.083
A1661: 988 | B1661: 156764 | C1661: 0 | D1661: JAIME ENRIQUE CARVAJAL ROA | E1661: 156764 | F1661: 28835.16 | G1661: 0 | H1661: 0 | I1661: 0 | J1661: 0 | K1661: 185599.16 | L1661: 1940439000 | M1661: 19404390-1 | N1661: BOGOTA - BOGOTA | O1661: E - COMMERCE | P1661: E - COMMERCE | Q1661: PVP | R1661: =E1661/$E$1757 -> 2.7502241e-06 | S1661: =Tabla3[[#This Row],[Subtotal]]/12 -> 13063.667
A1662: 123 | B1662: 156018 | C1662: 0 | D1662: BARBOZA PEREZ ESAYDA MARIA | E1662: 156018 | F1662: 27363.42 | G1662: 0 | H1662: 0 | I1662: 0 | J1662: 0 | K1662: 183381.42 | L1662: 6474192900 | M1662: 64741929 | N1662: BOGOTA - BOGOTA | O1662: TUL SAS | P1662: TUL SAS | Q1662: DISTRIBUIDOR | R1662: =E1662/$E$1757 -> 2.7371365e-06 | S1662: =Tabla3[[#This Row],[Subtotal]]/12 -> 13001.5
A1663: 178 | B1663: 153938 | C1663: 0 | D1663: CALDERON LINARES MARIA GLADYS/FERRE DEPOSITO J | E1663: 153938 | F1663: 29248.22 | G1663: 0 | H1663: 0 | I1663: 0 | J1663: 0 | K1663: 183186.22 | L1663: 3968682000 | M1663: 39686820-9 | N1663: BOGOTA - BOGOTA | O1663: ALFONSO ALBA - LOCALIDAD USAQUEN | P1663: ALFONSO ALBA - LOCALIDAD USAQUEN | Q1663: DISTRIBUIDOR | R1663: =E1663/$E$1757 -> 2.7006456e-06 | S1663: =Tabla3[[#This Row],[Subtotal]]/12 -> 12828.167
A1664: 175 | B1664: 148614 | C1664: 0 | D1664: CAJAMARCA LOPEZ CLAUDIA PATRICIA | E1664: 148614 | F1664: 28236.66 | G1664: 0 | H1664: 0 | I1664: 0 | J1664: 0 | K1664: 176850.66 | L1664: 3552519900 | M1664: 35525199-8 | N1664: MADRID - CUNDINAMARCA | O1664: DIANA ARENAS - SABANA OCCIDENTE | P1664: DIANA ARENAS - SABANA OCCIDENTE | Q1664: DISTRIBUIDOR | R1664: =E1664/$E$1757 -> 2.6072428e-06 | S1664: =Tabla3[[#This Row],[Subtotal]]/12 -> 12384.5
... A1712: 1466 | B1712: 63319 | C1712: 0 | D1712: RICARDO SIMON LALINDE | E1712: 63319 | F1712: 11080.61 | G1712: 0 | H1712: 0 | I1712: 0 | J1712: 0 | K1712: 74399.61 | L1712: 8008786700 | M1712: 80087867-3 | N1712: BOGOTA - BOGOTA | O1712: MOSTRADOR | P1712: MOSTRADOR | Q1712: PVP | R1712: =E1712/$E$1757 -> 1.110851e-06 | S1712: =Tabla3[[#This Row],[Subtotal]]/12 -> 5276.5833
A1713: 281 | B1713: 60102 | C1713: 0 | D1713: CESAR ANDRES CAVIATIVA BOLIVAR | E1713: 60102 | F1713: 11419.38 | G1713: 0 | H1713: 0 | I1713: 0 | J1713: 0 | K1713: 71521.38 | L1713: 101903634600 | M1713: 1019036346 | O1713: EMPLEADO | P1713: EMPLEADO | Q1713: INDUSTRIAL 2 | R1713: =E1713/$E$1757 -> 1.0544128e-06 | S1713: =Tabla3[[#This Row],[Subtotal]]/12 -> 5008.5
A1714: 155 | B1714: 59124 | C1714: 0 | D1714: BOTERO GIRALDO CLARA ELISA / DISTRIBUCIONES FAVAEL | E1714: 59124 | F1714: 11233.56 | G1714: 0 | H1714: 0 | I1714: 0 | J1714: 0 | K1714: 70357.56 | L1714: 5255455800 | M1714: 52554558-4 | N1714: BOGOTA - BOGOTA | O1714: ALFONSO ALBA - LOCALIDAD ENGATIVA | P1714: ALFONSO ALBA - LOCALIDAD ENGATIVA | Q1714: DISTRIBUIDOR | R1714: =E1714/$E$1757 -> 1.0372551e-06 | S1714: =Tabla3[[#This Row],[Subtotal]]/12 -> 4927
A1715: 81 | B1715: 58739.5 | C1715: 0 | D1715: ANA CAROLINA MELO ROJAS | E1715: 58739.5 | F1715: 11160.51 | G1715: 0 | H1715: 0 | I1715: 0 | J1715: 0 | K1715: 69900.01 | L1715: 102293834500 | M1715: 1022938345-3 | N1715: BOGOTA - BOGOTA | O1715: E - COMMERCE | P1715: E - COMMERCE | Q1715: ALMACEN DE PINTURAS | R1715: =E1715/$E$1757 -> 1.0305095e-06 | S1715: =Tabla3[[#This Row],[Subtotal]]/12 -> 4894.9583
A1716: 987 | B1716: 58319.33 | C1716: 0 | D1716: JACQUELINE FONSECA | E1716: 58319.33 | F1716: 11080.67 | G1716: 0 | H1716: 0 | I1716: 0 | J1716: 0 | K1716: 69400 | L1716: 2933009000 | M1716: 29330090 | N1716: BOGOTA - BOGOTA | O1716: E - COMMERCE | P1716: E - COMMERCE | Q1716: PVP | R1716: =E1716/$E$1757 -> 1.0231381e-06 | S1716: =Tabla3[[#This Row],[Subtotal]]/12 -> 4859.9442
A1717: 67 | B1717: 55588.24 | C1717: 0 | D1717: ALICIA ACOSTA | E1717: 55588.24 | F1717: 10561.77 | G1717: 0 | H1717: 0 | I1717: 0 | J1717: 0 | K1717: 66150.01 | L1717: 4143932600 | M1717: 41439326 | N1717: BOGOTA - BOGOTA | O1717: E - COMMERCE | P1717: E - COMMERCE | Q1717: PVP | R1717: =E1717/$E$1757 -> 9.7522466e-07 | S1717: =Tabla3[[#This Row],[Subtotal]]/12 -> 4632.3533
A1718: 379 | B1718: 53241 | C1718: 0 | D1718: CUERVO TORRES MARIA ISABEL/FERREIDEAS DEL SUR | E1718: 53241 | F1718: 10115.79 | G1718: 0 | H1718: 0 | I1718: 0 | J1718: 0 | K1718: 63356.79 | L1718: 3972037400 | M1718: 39720374-0 | N1718: BOGOTA - BOGOTA | O1718: NORMA AGUILAR - LOCALIDAD CIUDAD BOLIVAR | P1718: NORMA AGUILAR - LOCALIDAD CIUDAD BOLIVAR | Q1718: DISTRIBUIDOR | R1718: =E1718/$E$1757 -> 9.3404533e-07 | S1718: =Tabla3[[#This Row],[Subtotal]]/12 -> 4436.75
A1719: 1064 | B1719: 51428.57 | C1719: 0 | D1719: LEIDY JOHANNA PEREZ BERANCOURT | E1719: 51428.57 | F1719: 8821.43 | G1719: 0 | H1719: 0 | I1719: 0 | J1719: 0 | K1719: 60250 | L1719: 102659853700 | M1719: 1026598537 | N1719: BOGOTA - BOGOTA | O1719: E - COMMERCE | P1719: E - COMMERCE | Q1719: PVP | R1719: =E1719/$E$1757 -> 9.0224857e-07 | S1719: =Tabla3[[#This Row],[Subtotal]]/12 -> 4285.7142
A1720: 1279 | B1720: 48823.52 | C1720: 0 | D1720: ORLANDO LARGO PINEDA | E1720: 48823.52 | F1720: 9276.47 | G1720: 0 | H1720: 0 | I1720: 0 | J1720: 0 | K1720: 58099.99 | L1720: 7935883400 | M1720: 79358834 | N1720: BOGOTA - BOGOTA | O1720: E - COMMERCE | P1720: E - COMMERCE | Q1720: PVP | R1720: =E1720/$E$1757 -> 8.5654629e-07 | S1720: =Tabla3[[#This Row],[Subtotal]]/12 -> 4068.6267
A1721: 1063 | B1721: 46218.5 | C1721: 0 | D1721: LEIDY DUCUARA | E1721: 46218.5 | F1721: 8781.52 | G1721: 0 | H1721: 0 | I1721: 0 | J1721: 0 | K1721: 55000.02 | L1721: 107372065200 | M1721: 1073720652 | N1721: BOGOTA - BOGOTA | O1721: E - COMMERCE | P1721: E - COMMERCE | Q1721: PVP | R1721: =E1721/$E$1757 -> 8.1084454e-07 | S1721: =Tabla3[[#This Row],[Subtotal]]/12 -> 3851.5417
A1722: 1017 | B1722: 46050.42 | C1722: 0 | D1722: JULIO CESAR CARDENAS FANDIÑO | E1722: 46050.42 | F1722: 8749.58 | G1722: 0 | H1722: 0 | I1722: 0 | J1722: 0 | K1722: 54800 | L1722: 7948580000 | M1722: 79485800 | N1722: BOGOTA - BOGOTA | O1722: E - COMMERCE | P1722: E - COMMERCE | Q1722: PVP | R1722: =E1722/$E$1757 -> 8.0789579e-07 | S1722: =Tabla3[[#This Row],[Subtotal]]/12 -> 3837.535
A1723: 1072 | B1723: 45125 | C1723: 0 | D1723: LINA MARIA QUINTERO BOHORQUEZ | E1723: 45125 | F1723: 7623.75 | G1723: 0 | H1723: 0 | I1723: 0 | J1723: 0 | K1723: 52748.75 | L1723: 101539310400 | M1723: 101593104 | N1723: BOGOTA - BOGOTA | O1723: E - COMMERCE | P1723: E - COMMERCE | Q1723: PVP | R1723: =E1723/$E$1757 -> 7.9166048e-07 | S1723: =Tabla3[[#This Row],[Subtotal]]/12 -> 3760.4167
A1724: 408 | B1724: 44286 | C1724: 0 | D1724: DENNISE PAOLA LINDO MEDINA | E1724: 44286 | F1724: 7464.34 | G1724: 0 | H1724: 0 | I1724: 0 | J1724: 0 | K1724: 51750.34 | L1724: 101419544400 | M1724: 1014195444-5 | N1724: BOGOTA - BOGOTA | O1724: E - COMMERCE | P1724: E - COMMERCE | Q1724: PVP | R1724: =E1724/$E$1757 -> 7.769413e-07 | S1724: =Tabla3[[#This Row],[Subtotal]]/12 -> 3690.5
A1725: 203 | B1725: 42941.38 | C1725: 0 | D1725: CARLOS EDUARDO RAMIREZ PINZON | E1725: 42941.38 | F1725: 8158.86 | G1725: 0 | H1725: 0 | I1725: 0 | J1725: 0 | K1725: 51100.24 | L1725: 7952380100 | M1725: 79523801 | N1725: BOGOTA - BOGOTA | O1725: E - COMMERCE | P1725: E - COMMERCE | Q1725: PVP | R1725: =E1725/$E$1757 -> 7.5335166e-07 | S1725: =Tabla3[[#This Row],[Subtotal]]/12 -> 3578.4483
... A1756: 393 | B1756: -1477962 | C1756: 0 | D1756: CYRGO S.A.S-VILLAVICENCIO | E1756: -1477962 | F1756: -280812.78 | G1756: -40812.75 | H1756: -42121.92 | I1756: 0 | J1756: -82934.67 | K1756: -1675840.1 | L1756: 86000969407 | M1756: 860009694-2 | N1756: VILLAVICENCIO - META | O1756: WILSON SEPULVEDA - META | P1756: WILSON SEPULVEDA - META | Q1756: MAYORISTA INDUSTRIAL | R1756: =E1756/$E$1757 -> -2.5928955e-05 | S1756: =Tabla3[[#This Row],[Subtotal]]/12 -> -123163.5
E1757: =SUM(E2:E1753) -> 5.7000445e+10 | S1757: =Tabla3[[#This Row],[Subtotal]]/12 -> 4.7500371e+09

Sheet Detalle Vendedores
B2: PARTICIPACIÓN GENERAL | F2: CRECIMIENTO VS 2024 | L2: CRECIMIENTO DETALLADO X ZONA VS 2024
B3: Asesor Comercial | C3: Participacion % | D3: Participacion $ (MM) | F3: Asesor Comercial | G3: VENTAS 2024 | H3: VENTAS 2025 | I3: CRECIMIENTO | L3: Asesor Comercial | M3: Zona | N3: VENTAS 2024 | O3: VENTAS 2025 | P3: CRECIMIENTO | Q3: PARTICIPACIÓN ZONA 2025
B4: Jorge Castro | C4: 0.2425 | D4: 13823 | F4: Jorge Castro | G4: 11489023266 | H4: 13823417353 | I4: =(H4-G4)/H4 -> 0.16887243 | K4: ASESORES VIAJEROS | L4: Jorge Castro | M4: Valle Del Cauca | N4: 6927872874 | O4: 7558893415 | P4: =(O4-N4)/O4 -> 0.083480545 | Q4: =O4/'2025'!$E$1757 -> 0.13261113 | R4: =SUM(Q4:Q8) -> 0.24233774
B5: Grandes Cuentas | C5: 0.138 | D5: 7866 | F5: Grandes Cuentas | G5: 7367703218 | H5: 8238296111 | I5: =(H5-G5)/H5 -> 0.10567633 | M5: Eje Cafetero | N5: 2018866302 | O5: 2816248608 | P5: =(O5-N5)/O5 -> 0.28313633 | Q5: =O5/'2025'!$E$1757 -> 0.049407484
B6: Omar Montaña | C6: 0.1354 | D6: 7718 | F6: Omar Montaña | G6: 7056073629 | H6: 7718923702 | I6: =(H6-G6)/H6 -> 0.085873381 | M6: Cauca | N6: 1748089511 | O6: 2246645092 | P6: =(O6-N6)/O6 -> 0.22191114 | Q6: =O6/'2025'!$E$1757 -> 0.039414518
B7: Wilson Sepulveda | C7: 0.12 | D7: 6841 | F7: Wilson Sepulveda | G7: 5468134228 | H7: 6841728666 | I7: =(H7-G7)/H7 -> 0.20076716 | M7: Nariño | N7: 733534298 | O7: 1101381379 | P7: =(O7-N7)/O7 -> 0.33398702 | Q7: =O7/'2025'!$E$1757 -> 0.019322329
B8: Evelio Garcia | C8: 0.1026 | D8: 5847 | F8: Evelio Garcia | G8: 5584181528 | H8: 5847496154 | I8: =(H8-G8)/H8 -> 0.045030321 | M8: Putumayo | N8: 60669280 | O8: 90190834 | P8: =(O8-N8)/O8 -> 0.32732322 | Q8: =O8/'2025'!$E$1757 -> 0.001582283
B9: Antioquia | C9: 0.0479 | D9: 2732 | F9: Antioquia | G9: 2544954537 | H9: 2732456699 | I9: =(H9-G9)/H9 -> 0.06862036 | L9: Omar Montaña | M9: Tolima Sur | N9: 2936016665 | O9: 3327966394 | P9: =(O9-N9)/O11 -> 0.35945675 | Q9: =O9/'2025'!$E$1757 -> 0.058384919 | R9: =SUM(Q9:Q11) -> 0.13541866
B10: Institucional/Industrial | C10: 0.0449 | D10: 2558 | F10: Institucional/Industrial | G10: 2423357672 | H10: 2558604467 | I10: =(H10-G10)/H10 -> 0.052859595 | M10: Sabana Centro | N10: 3128272264 | O10: 3300562610 | P10: =(O10-N10)/O9 -> 0.051770458 | Q10: =O10/'2025'!$E$1757 -> 0.057904155
B11: Norma Aguilar | C11: 0.0398 | D11: 2269 | F11: Norma Aguilar | G11: 2123335456 | H11: 2269767081 | I11: =(H11-G11)/H11 -> 0.064513943 | M11: Tolima Norte | N11: 991774699 | O11: 1090394698 | P11: =(O11-N11)/O10 -> 0.029879754 | Q11: =O11/'2025'!$E$1757 -> 0.019129582
B12: Cristian Betancourt | C12: 0.0316 | D12: 1801 | F12: Cristian Betancourt | G12: 1101238952 | H12: 1429925803 | I12: =(H12-G12)/H12 -> 0.22986287 | L12: Wilson Sepulveda | M12: Huila-Caqueta | N12: 2914498252 | O12: 3803245626 | P12: =(O12-N12)/O12 -> 0.2336813 | Q12: =O12/'2025'!$E$1757 -> 0.066723086 | R12: =SUM(Q12:Q16) -> 0.12002939
B13: Diana Arenas | C13: 0.0296 | D13: 1687 | F13: Diana Arenas | G13: 1476650679 | H13: 1687814401 | I13: =(H13-G13)/H13 -> 0.12511075 | M13: Meta | N13: 1157826909 | O13: 1342010763 | P13: =(O13-N13)/O13 -> 0.13724469 | Q13: =O13/'2025'!$E$1757 -> 0.023543865
B14: Alfonso Alba | C14: 0.0271 | D14: 1545 | F14: Alfonso Alba | G14: 1587407347 | H14: 1545341238 | I14: =(H14-G14)/H14 -> -0.027221243 | M14: Boyaca | N14: 867458814 | O14: 1055139783 | P14: =(O14-N14)/O14 -> 0.17787309 | Q14: =O14/'2025'!$E$1757 -> 0.01851108
B15: Alejandro Caranton | C15: 0.0179 | D15: 1022 | F15: Alejandro Caranton | G15: 952099324 | H15: 1022425687 | I15: =(H15-G15)/H15 -> 0.068783838 | M15: Guaviare | N15: 326326498 | O15: 370177128 | P15: =(O15-N15)/O15 -> 0.11845851 | Q15: =O15/'2025'!$E$1757 -> 0.0064942848
B16: TOTAL | C16: =SUM(C4:C15) -> 0.9773 | D16: =SUM(D4:D15) -> 55709 | F16: TOTAL | G16: =SUM(G4:G15) -> 49174159836 | H16: =SUM(H4:H15) -> 55716197362 | M16: Casanare | N16: 202023754 | O16: 271155366 | P16: =(O16-N16)/O16 -> 0.25495203 | Q16: =O16/'2025'!$E$1757 -> 0.0047570745
L17: Evelio Garcia | M17: Santander | N17: 4248642582 | O17: 4388642074 | P17: =(O17-N17)/O17 -> 0.031900412 | Q17: =O17/'2025'!$E$1757 -> 0.076993119 | R17: =SUM(Q17:Q21) -> 0.10258685
M18: Norte del Santander | N18: 864987728 | O18: 892894634 | P18: =(O18-N18)/O18 -> 0.031254422 | Q18: =O18/'2025'!$E$1757 -> 0.015664696
M19: Cesar | N19: 342602428 | O19: 450234194 | P19: =(O19-N19)/O19 -> 0.23905729 | Q19: =O19/'2025'!$E$1757 -> 0.0078987838
M20: Santander 2 | N20: 109771657 | O20: 103293534 | P20: =(O20-N20)/O20 -> -0.062715668 | Q20: =O20/'2025'!$E$1757 -> 0.0018121531
B21: CRECIMIENTO CLIENTES VS 2024 | M21: Arauca | N21: 18177132 | O21: 12431718 | P21: =(O21-N21)/O21 -> -0.46215768 | Q21: =O21/'2025'!$E$1757 -> 0.00021809861
B22: CLIENTE | C22: CASTILLO MATEUS ALFRED NEY/NEY PINTURAS | L22: Cristian Betancourt | M22: Costa Norte | N22: 556794398 | O22: 689396605 | P22: =(O22-N22)/O22 -> 0.19234531 | Q22: =O22/'2025'!$E$1757 -> 0.012094583 | R22: =SUM(Q22:Q24) -> 0.025086222
B23: VENTAS 2024 | C23: =VLOOKUP(C22,'2024'!D1:E2033,2,FALSE) -> 30146177 | M23: Costa Centro | N23: 378092078 | O23: 479462732 | P23: =(O23-N23)/O23 -> 0.21142551 | Q23: =O23/'2025'!$E$1757 -> 0.0084115612
B24: VENTAS 2025 | C24: =VLOOKUP(C22,'2025'!D2:E2034,2,FALSE) -> 10466798 | M24: Costa Sur | N24: 166352476 | O24: 261066466 | P24: =(O24-N24)/O24 -> 0.36279646 | Q24: =O24/'2025'!$E$1757 -> 0.0045800777
B25: CRECIMIENTO | C25: =(C24-C23)/C24 -> -1.8801718 | K25: ASESORTES BOGOTA | L25: Norma Aguilar | M25: Ciudad Bolivar | N25: 93310279 | O25: 90018093 | P25: =(O25-N25)/O25 -> -0.036572492 | Q25: =O25/'2025'!$E$1757 -> 0.0015792525 | R25: =SUM(Q25:Q31) -> 0.039820164
M26: Candelaria | N26: 34960963 | O26: 35709766 | P26: =(O26-N26)/O26 -> 0.020969138 | Q26: =O26/'2025'!$E$1757 -> 0.00062648223
M27: Martires | N27: 1141683970 | O27: 1282647094 | P27: =(O27-N27)/O27 -> 0.10990016 | Q27: =O27/'2025'!$E$1757 -> 0.022502405
M28: Puente Aranda | N28: 386935898 | O28: 335985167 | P28: =(O28-N28)/O28 -> -0.15164577 | Q28: =O28/'2025'!$E$1757 -> 0.0058944306
M29: San Cristobal | N29: 124839552 | O29: 146275291 | P29: =(O29-N29)/O29 -> 0.14654381 | Q29: =O29/'2025'!$E$1757 -> 0.0025662131
M30: Santafe | N30: 160721572 | O30: 165918418 | P30: =(O30-N30)/O30 -> 0.031321694 | Q30: =O30/'2025'!$E$1757 -> 0.0029108267
M31: Usme | N31: 177883222 | O31: 213213252 | P31: =(O31-N31)/O31 -> 0.16570279 | Q31: =O31/'2025'!$E$1757 -> 0.0037405541
L32: Diana Arenas | M32: Barrios Unidos | N32: 823520526 | O32: 872573530 | P32: =(O32-N32)/O32 -> 0.05621647 | Q32: =O32/'2025'!$E$1757 -> 0.015308188 | R32: =SUM(Q32:Q36) -> 0.029610548
M33: Chapinero | N33: 76148423 | O33: 142651404 | P33: =(O33-N33)/O33 -> 0.46619226 | Q33: =O33/'2025'!$E$1757 -> 0.0025026367
M34: Fontibon | N34: 154808223 | O34: 145783896 | P34: =(O34-N34)/O34 -> -0.061902084 | Q34: =O34/'2025'!$E$1757 -> 0.0025575922
M35: Teusaquillo | N35: 46668269 | O35: 39177746 | P35: =(O35-N35)/O35 -> -0.19119331 | Q35: =O35/'2025'!$E$1757 -> 0.00068732351
M36: Sabana Occidente | N36: 375505249 | O36: 487627825 | P36: =(O36-N36)/O36 -> 0.22993474 | Q36: =O36/'2025'!$E$1757 -> 0.0085548073
L37: Alfonso Alba | M37: Suba | N37: 895985135 | O37: 846450739 | P37: =(O37-N37)/O37 -> -0.058520117 | Q37: =O37/'2025'!$E$1757 -> 0.014849897 | R37: =SUM(Q37:Q39) -> 0.027111038
M38: Engativa | N38: 433051305 | O38: 456230961 | P38: =(O38-N38)/O38 -> 0.050806846 | Q38: =O38/'2025'!$E$1757 -> 0.0080039894
M39: Usaquen | N39: 258370907 | O39: 242659538 | P39: =(O39-N39)/O39 -> -0.064746554 | Q39: =O39/'2025'!$E$1757 -> 0.0042571516
L40: Alejandro Caranton | M40: Antonio Nariño | N40: 62567596 | O40: 63810617 | P40: =(O40-N40)/O40 -> 0.019479846 | Q40: =O40/'2025'!$E$1757 -> 0.0011194758 | R40: =SUM(Q40:Q45) -> 0.017937205
M41: Bosa | N41: 175565667 | O41: 240169438 | P41: =(O41-N41)/O41 -> 0.26899247 | Q41: =O41/'2025'!$E$1757 -> 0.004213466
M42: Kennedy | N42: 345830620 | O42: 333082633 | P42: =(O42-N42)/O42 -> -0.038272746 | Q42: =O42/'2025'!$E$1757 -> 0.0058435093
M43: Rafael Uribe Uribe | N43: 174374765 | O43: 171045695 | P43: =(O43-N43)/O43 -> -0.019463045 | Q43: =O43/'2025'!$E$1757 -> 0.0030007782
M44: Tunjuelito | N44: 72842817 | O44: 73534609 | P44: =(O44-N44)/O44 -> 0.0094077062 | Q44: =O44/'2025'!$E$1757 -> 0.0012900708
M45: Soacha - Sibate | N45: 120947859 | O45: 140785694 | P45: =(O45-N45)/O45 -> 0.14090803 | Q45: =O45/'2025'!$E$1757 -> 0.0024699052
